Workbook

Sheet LÉEME
B1: MONIFIC × BNO — Matriz única de hallazgos (documento de trabajo)
B2: 4 auditorías + dictamen de BNO + validación Monific (Raquel) + estado de TI (Daniel)
B3: Corte: 18-jun-2026 · Portal HubSpot 48427391 · 284 hallazgos de auditoría + 81 comunicaciones TO BE · Corte oficial: 251 abiertos = 217 exigibles a BNO (84 críticos, 87 altos, 37 medios, 9 bajos) + 2 controles informativos + 32 no exigidos.
B5: QUÉ ES ESTE ARCHIVO
B6: Una sola fuente de verdad para el cierre con BNO: reúne en la hoja «Hallazgos consolidados» todo lo detectado en las 4 auditorías, con qué dijo BNO, qué falta validar Monific y qué ya resolvió TI (Monific).
B8: FUENTES (columna «Origen»)
B9: • 1ª Auditoría (+ dictamen BNO): 112 hallazgos. Se usa la versión «Comentarios BNO» = la 1ª con la columna de dictamen de BNO llena.
B10: • 2ª Auditoría: 109 registros de re-validación; donde aplica indica qué fila de la 1ª pasada actualiza.
B11: • 3ª Bitácora técnica: 57 hallazgos APP-001 a APP-057 (API / propiedades / apps privadas).
B12: • 4ª Auditoría de Comunicaciones: AS-IS van en «Hallazgos consolidados»; las 81 comunicaciones (0 implementadas) viven en su pestaña «Comunicaciones (81)».
B13: Evidencia Auditoría API HubSpot (17-jun-2026): Se realizó una extracción directamente desde HubSpot para documentar el estado real de la cuenta, sin depender de interpretaciones manuales ni de información declarada por BNO. La evidencia está concentrada en las pestañas «WF estado real (96)», «Verificación 31 propiedades», «Auditoría API 17-jun», «WF lógica (detalle API)» y «Acceso y config (API)». Esta auditoría confirma, con datos obtenidos directamente por API, los siguientes puntos: Workflows apagados: se identificó el estado real de los 96 workflows existentes. Propiedades no creadas por BNO: se verificó cuáles de las 31 propiedades comprometidas no existen en HubSpot. Objeto de Cobranza inexistente: se confirmó que el objeto personalizado de Cobranza no fue creado. Accesos activos no regularizados: aún existen usuarios de BNO y usuarios externos con acceso a la cuenta. Lógica interna auditada: además del estado general, se revisó la lógica interna de los 96 workflows, con un total de 4,848 nodos verificados.
B15: COLUMNAS DE CONTROL
... B31: Aclaración de autoría: los masters de implementación y los flujogramas yson entregables de BNO derivados del discovery contratado (Add-On Mapeo de Procesos), NO insumos de Monific. Monific solo participó, revisó, autorizó y corrigió; su elaboración y depuración son responsabilidad de BNO.

Sheet Tablero
B1: MONIFIC × BNO — Tablero de cierre (en vivo)
B2: Se actualiza solo conforme marcas la validación y cambian los estatus de TI y de comunicaciones.
B4: Indicador | C4: Avance | D4: % | E4: Barra
B5: Hallazgos en seguimiento — abiertos (en vivo) | C5: =(COUNTIF('Hallazgos consolidados'!$N$2:$N$5000,"Sigue mal (abierto)")+COUNTIF('Hallazgos consolidados'!$N$2:$N$5000,"Sigue mal — BNO reconoció que aplica")+COUNTIF('Hallazgos consolidados'!$N$2:$N$5000,"Sigue mal — verificado por API")+COUNTIF('Hallazgos consolidados'!$N$2:$N$5000,"BNO documentó resuelto pero sigue mal")+COUNTIF('Hallazgos consolidados'!$N$2:$N$5000,"Bloqueado — pendiente decisión Monific")+COUNTIF('Hallazgos consolidados'!$N$2:$N$5000,"En curso (BNO)")+COUNTIF('Hallazgos consolidados'!$N$2:$N$5000,"Pendiente — BNO debe definir")+COUNTIF('Hallazgos consolidados'!$N$2:$N$5000,"Pendiente — TI Monific"))&" / "&COUNTA('Hallazgos consolidados'!$A$2:$A$5000) -> 249 / 284 | D5: =IFERROR((COUNTIF('Hallazgos consolidados'!$N$2:$N$5000,"Sigue mal (abierto)")+COUNTIF('Hallazgos consolidados'!$N$2:$N$5000,"Sigue mal — BNO reconoció que aplica")+COUNTIF('Hallazgos consolidados'!$N$2:$N$5000,"Sigue mal — verificado por API")+COUNTIF('Hallazgos consolidados'!$N$2:$N$5000,"BNO documentó resuelto pero sigue mal")+COUNTIF('Hallazgos consolidados'!$N$2:$N$5000,"Bloqueado — pendiente decisión Monific")+COUNTIF('Hallazgos consolidados'!$N$2:$N$5000,"En curso (BNO)")+COUNTIF('Hallazgos consolidados'!$N$2:$N$5000,"Pendiente — BNO debe definir")+COUNTIF('Hallazgos consolidados'!$N$2:$N$5000,"Pendiente — TI Monific"))/COUNTA('Hallazgos consolidados'!$A$2:$A$5000),0) -> 0.87676056 | E5: =REPT("█",MAX(0,MIN(20,ROUND(D5*20,0))))&REPT("░",20-MAX(0,MIN(20,ROUND(D5*20,0)))) -> ██████████████████░░
B6: Hallazgos resueltos o validados | C6: =(COUNTIF('Hallazgos consolidados'!$N$2:$N$5000,"Validado (resuelto)")+COUNTIF('Hallazgos consolidados'!$N$2:$N$5000,"Resuelto (con pendiente menor)")+COUNTIF('Hallazgos consolidados'!$N$2:$N$5000,"Resuelto pendiente de confirmar")+COUNTIF('Hallazgos consolidados'!$N$2:$N$5000,"Resuelto por TI Monific (Daniel)"))&" / "&COUNTA('Hallazgos consolidados'!$A$2:$A$5000) -> 18 / 284 | D6: =IFERROR((COUNTIF('Hallazgos consolidados'!$N$2:$N$5000,"Validado (resuelto)")+COUNTIF('Hallazgos consolidados'!$N$2:$N$5000,"Resuelto (con pendiente menor)")+COUNTIF('Hallazgos consolidados'!$N$2:$N$5000,"Resuelto pendiente de confirmar")+COUNTIF('Hallazgos consolidados'!$N$2:$N$5000,"Resuelto por TI Monific (Daniel)"))/COUNTA('Hallazgos consolidados'!$A$2:$A$5000),0) -> 0.063380282 | E6: =REPT("█",MAX(0,MIN(20,ROUND(D6*20,0))))&REPT("░",20-MAX(0,MIN(20,ROUND(D6*20,0)))) -> █░░░░░░░░░░░░░░░░░░░
B7: Defectos que BNO reconoció y siguen abiertos | C7: =COUNTIF('Hallazgos consolidados'!$N$2:$N$5000,"Sigue mal — BNO reconoció que aplica")&" / "&COUNTA('Hallazgos consolidados'!$A$2:$A$5000) -> 103 / 284 | D7: =IFERROR(COUNTIF('Hallazgos consolidados'!$N$2:$N$5000,"Sigue mal — BNO reconoció que aplica")/COUNTA('Hallazgos consolidados'!$A$2:$A$5000),0) -> 0.36267606 | E7: =REPT("█",MAX(0,MIN(20,ROUND(D7*20,0))))&REPT("░",20-MAX(0,MIN(20,ROUND(D7*20,0)))) -> ███████░░░░░░░░░░░░░
B8: Acciones de TI (Daniel) cerradas | C8: =COUNTIF('Hallazgos consolidados'!$O$2:$O$5000,"Sí – Daniel (hecho)")&" / "&(COUNTIF('Hallazgos consolidados'!$O$2:$O$5000,"Sí – Daniel (hecho)")+COUNTIF('Hallazgos consolidados'!$O$2:$O$5000,"Pendiente TI")+COUNTIF('Hallazgos consolidados'!$O$2:$O$5000,"Condicionado a BNO")) -> 12 / 20 | D8: =IFERROR(COUNTIF('Hallazgos consolidados'!$O$2:$O$5000,"Sí – Daniel (hecho)")/(COUNTIF('Hallazgos consolidados'!$O$2:$O$5000,"Sí – Daniel (hecho)")+COUNTIF('Hallazgos consolidados'!$O$2:$O$5000,"Pendiente TI")+COUNTIF('Hallazgos consolidados'!$O$2:$O$5000,"Condicionado a BNO")),0) -> 0.6 | E8: =REPT("█",MAX(0,MIN(20,ROUND(D8*20,0))))&REPT("░",20-MAX(0,MIN(20,ROUND(D8*20,0)))) -> ████████████░░░░░░░░
B9: Comunicaciones construidas (de 81) | C9: =(COUNTA('Comunicaciones (81)'!$A$2:$A$5000)-COUNTIF('Comunicaciones (81)'!$L$2:$L$5000,"No iniciado"))&" / "&COUNTA('Comunicaciones (81)'!$A$2:$A$5000) -> 0 / 81 | D9: =IFERROR((COUNTA('Comunicaciones (81)'!$A$2:$A$5000)-COUNTIF('Comunicaciones (81)'!$L$2:$L$5000,"No iniciado"))/COUNTA('Comunicaciones (81)'!$A$2:$A$5000),0) -> 0 | E9: =REPT("█",MAX(0,MIN(20,ROUND(D9*20,0))))&REPT("░",20-MAX(0,MIN(20,ROUND(D9*20,0)))) -> ░░░░░░░░░░░░░░░░░░░░
B11: Contexto (no es %) | C11: Valor
B12: Pendientes exigibles a BNO (corte del requerimiento) | C12: =COUNTIF('Hallazgos consolidados'!$W$2:$W$5000,"Sí") -> 217
B13: — de ellos, críticos exigibles a BNO | C13: =COUNTIFS('Hallazgos consolidados'!$W$2:$W$5000,"Sí",'Hallazgos consolidados'!$I$2:$I$5000,"Crítico") -> 84
B14: Total hallazgos / comunicaciones | C14: =COUNTA('Hallazgos consolidados'!$A$2:$A$5000)&" / "&COUNTA('Comunicaciones (81)'!$A$2:$A$5000) -> 284 / 81
B15: Conciliación del corte oficial: 284 = 18 resueltos + 15 descartados + 251 abiertos. Los 251 abiertos = 217 exigibles a BNO + 2 controles informativos (CON-216/217) + 32 no exigidos directamente a BNO. Críticos exigibles a BNO: 84 (87 altos, 37 medios, 9 bajos). Las barras de arriba son seguimiento operativo en vivo y pueden variar mientras Raquel valida cada fila.
B16: Qué estado de validación mueve qué (para que sepas el efecto al cambiar una fila):
B17: • Suma a «Siguen mal / abiertos»: Sigue mal (abierto), Sigue mal — BNO reconoció que aplica, Sigue mal — verificado por API, BNO documentó resuelto pero sigue mal, Bloqueado — pendiente decisión Monific, En curso (BNO), Pendiente — BNO debe definir, Pendiente — TI Monific
B18: • Suma a «Resueltos / validados»: Validado (resuelto), Resuelto (con pendiente menor), Resuelto pendiente de confirmar, Resuelto por TI Monific (Daniel)
B19: • Neutrales (no mueven ninguna barra): Descartado por acuerdo de alcance (revisar), No aplica / informativo, Sin evidencia objetiva — revisar
B21: Cómo leerlo: las barras y % suben solos al cambiar la columna «Validación Monific (Raquel)» o los estatus. Edita en Excel o Google Sheets (no en PDF).
B23: Estado real en HubSpot (API · 17-jun-2026) — snapshot, no cambia solo | C23: Avance | D23: % | E23: Barra
B24: Workflows activos (ON) en HubSpot | C24: =COUNTIF('WF estado real (96)'!$C$2:$C$5000,"ON")&" / "&COUNTA('WF estado real (96)'!$A$2:$A$5000) -> 57 / 96 | D24: =IFERROR(COUNTIF('WF estado real (96)'!$C$2:$C$5000,"ON")/COUNTA('WF estado real (96)'!$A$2:$A$5000),0) -> 0.59375 | E24: =REPT("█",MAX(0,MIN(20,ROUND(D24*20,0))))&REPT("░",20-MAX(0,MIN(20,ROUND(D24*20,0)))) -> ████████████░░░░░░░░
B25: Propiedades de las 31 de BNO creadas | C25: =COUNTIF('Verificación 31 propiedades'!$H$2:$H$5000,"EXISTE*")&" / 31" -> 5 / 31 | D25: =IFERROR(COUNTIF('Verificación 31 propiedades'!$H$2:$H$5000,"EXISTE*")/31,0) -> 0.16129032 | E25: =REPT("█",MAX(0,MIN(20,ROUND(D25*20,0))))&REPT("░",20-MAX(0,MIN(20,ROUND(D25*20,0)))) -> ███░░░░░░░░░░░░░░░░░
B26: Workflows que comunican al cliente (de 96) | C26: =9&" / 96" -> 9 / 96 | D26: =IFERROR(9/96,0) -> 0.09375 | E26: =REPT("█",MAX(0,MIN(20,ROUND(D26*20,0))))&REPT("░",20-MAX(0,MIN(20,ROUND(D26*20,0)))) -> ██░░░░░░░░░░░░░░░░░░

Sheet Hallazgos consolidados
A1: ID | B1: Origen | C1: ID origen | D1: Tipo de registro | E1: Proceso / Pipeline | F1: WF | G1: Hallazgo | H1: Severidad (orig.) | I1: Prioridad (norm.) | J1: Estado (según auditoría) | K1: Responsable (según auditoría) | L1: Quién debe actuar (norm.) | M1: Dictamen / Comentario de BNO | N1: Validación Monific (Raquel) | O1: Resuelto por TI (Daniel) | P1: Ref. punto TI | Q1: Acción correctiva / propuesta | R1: Evidencia | S1: Notas / vínculo | T1: Sustento de validación | U1: Fecha detección (auditoría) | V1: Fecha validación Monific | W1: Exigible BNO (canónico)
A2: CON-001 | B2: 1ª Auditoría (+ dictamen BNO) | C2: WF-001 · f1 | D2: Hallazgo base | F2: WF-001 | G2: La carpeta Drive del solicitante se crea 100% manual por el asesor. La integración HubSpot↔Drive (marzo 2026) no se está usando, así que se pierde la automatización. | H2: Alto | I2: Alto | J2: Abierto | K2: BNO – Implementación | L2: BNO | M2: Sesión 19-may NO aplicado: la integración nativa no replica plantillas con estructura. Solución: Apps Script externo. Reasignado a BNO/Tech Monific. | N2: BNO documentó resuelto pero sigue mal | O2: No aplica | Q2: Ver posibilidad de usar la acción nativa 'Crear carpeta' de la integración, o un webhook a Apps Script, para que la carpeta se cree sola con nomenclatura estándar, permisos por rol y URL persistida en el Negocio. La tarea al asesor debería ser solo enviar el link. | S2: Master de Implementación_ Proceso Comercial - Monific | T2: BNO documentó acción pero quedó NO aplicado; auditoría: Abierto | U2: 2026-05-18 | V2: 46191 | W2: Sí
A3: CON-002 | B3: 1ª Auditoría (+ dictamen BNO) | C3: WF-001 · f2 | D3: Hallazgo base | F3: WF-001 | G3: La tarea creada al asesor tenía vencimiento a 5 días laborables y recordatorio al día 3, pero NO había paso de escalamiento si la tarea no se completaba. | H3: Alto | I3: Alto | J3: Resuelto | K3: BNO – Implementación | L3: BNO | M3: APLICADO: se agregaron al WF-001 las acciones de retraso 6 días laborables + ramificación 'Estado de tarea ≠ Terminada' + email de escalamiento a Karen Gómez. Sin reasignación de ownership porque Karen | N3: Validado (resuelto) | O3: No aplica | Q3: Crear WF de escalamiento que detecte la tarea vencida al día 5+1 y notifique al superior (Karen) por email, además de reasignar la tarea. | S3: Master de Implementación_ Proceso Comercial - Monific | T3: Auditoría: Resuelto y aplicado | U3: 2026-05-18 | V3: 46191 | W3: No
A4: CON-003 | B4: 1ª Auditoría (+ dictamen BNO) | C4: WF-001 · f3 | D4: Hallazgo base | F4: WF-001 | G4: Los vencimientos y recordatorios de tareas se calculaban en UTC-04, pero Monific opera en CDMX (UTC-06). Resultado: las tareas se disparaban con 2 horas de desfase respecto al día laboral mexicano. | H4: Medio | I4: Medio | J4: Resuelto | K4: BNO – Arquitectura | L4: BNO | M4: APLICADO. Zona horaria cambiada a UTC-06 CDMX y persistida tras recarga. Pendiente: BNO revisar WFs Solicitantes que leen horarios fijos. | N4: Resuelto (con pendiente menor) | O4: No aplica | Q4: Cambiar zona horaria de la cuenta HubSpot a America/Mexico_City (UTC-06). Validar que todos los WFs que leen '8:00' o '9:00' sigan teniendo sentido en CDMX. | S4: Master de Implementación_ Proceso Comercial - Monific | T4: Auditoría: Resuelto, con pendiente menor en el dictamen | U4: 2026-05-18 | V4: 46191 | W4: No
A5: CON-004 | B5: 1ª Auditoría (+ dictamen BNO) | C5: WF-002 · f4 | D5: Hallazgo base | F5: WF-002 | G5: El WF mueve el negocio de Nuevo a Evaluación sin dejar registro de quién/cuándo. | H5: Medio | I5: Medio | J5: Descartado | K5: Monific – Raquel | L5: Monific – negocio (Raquel) | M5: Validado por BNO. Se mantiene descartado para MVP por decisión de alcance. Aunque la trazabilidad es recomendable, Monific decidió no incorporarlo en esta etapa. | N5: Descartado por acuerdo de alcance (revisar) | O5: No aplica | Q5: Agregar acciones que escriban 'Fecha de entrada a Evaluación' y 'Origen del cambio = Automático WF-002' antes del cambio de etapa. | S5: Master de Implementación_ Proceso Comercial - Monific | T5: Auditoría: Descartado (decisión de alcance/MVP) — revisar si Monific lo acepta | U5: 2026-05-18 | V5: 46191 | W5: No
A6: CON-005 | B6: 1ª Auditoría (+ dictamen BNO) | C6: WF-002 · f5 | D6: Hallazgo base | F6: WF-002 | G6: Reinscripción apagada. Si un solicitante fue rechazado y se devuelve a Nuevo para retrabajo, al volver a tener documentación completa NO se mueve automáticamente a Evaluación, queda atorado y obliga al asesor a moverlo a mano. | H6: Medio | I6: Medio | J6: Bloqueado | K6: Monific – Raquel | L6: Monific – negocio (Raquel) | M6: Validado por BNO. Se mantiene bloqueado/pendiente de decisión Comercial. Si Monific decide automatizar reingresos a Nuevo, se debe activar reinscripción con condiciones acotadas para evitar movimientos duplicados. | N6: Bloqueado — pendiente decisión Monific | O6: No aplica | Q6: Decidir con Comercial si se quiere reinscripción automática al re-entrar a Nuevo con documentación completa. Si sí, activar reinscripción. | S6: Master de Implementación_ Proceso Comercial - Monific | T6: Auditoría: Bloqueado; BNO lo dejó a decisión de Monific | U6: 2026-05-18 | V6: 46191 | W6: No
A7: CON-006 | B7: 1ª Auditoría (+ dictamen BNO) | C7: WF-003 · f6 | D7: Hallazgo base | F7: WF-003 | G7: Cuando un solicitante entra a Nuevo con documentación ya completa, WF-002 y WF-003 se disparan en paralelo: uno lo mueve a Evaluación, el otro lo pone En pausa y lo inscribe en secuencia. Resultado: estado inconsistente. | H7: Alto | I7: Alto | J7: Abierto | K7: BNO – Implementación | L7: BNO | M7: Validado por BNO. El hallazgo aplica: WF-002 y WF-003 deben quedar mutuamente excluyentes para evitar estados inconsistentes. Ajustar condición de WF-003 para excluir documentación completa y probar caso de ingreso con documentación completa. | N7: Sigue mal — BNO reconoció que aplica | O7: No aplica | Q7: Agregar al WF-003 la condición 'Estatus de documentación NO es Completa' para que ambos WFs sean mutuamente excluyentes. | S7: Master de Implementación_ Proceso Comercial - Monific | T7: Auditoría: Abierto; BNO validó por escrito que el hallazgo APLICA | U7: 2026-05-18 | V7: 46191 | W7: Sí
A8: CON-007 | B8: 1ª Auditoría (+ dictamen BNO) | C8: WF-003 · f7 | D8: Hallazgo base | F8: WF-003 | G8: El WF marca la bandera 'Inscribir en secuencia +15 días' sobre TODOS los contactos asociados al negocio. Si el negocio tiene varios contactos (solicitante + asesor interno + apoderado), todos reciben la secuencia diseñada para el solicitante. | H8: Medio | I8: Medio | J8: Abierto | K8: BNO – Implementación | L8: BNO | M8: Validado por BNO. Aplica como ajuste de seguridad operativa. Se debe filtrar la actualización de bandera solo al rol de contacto correspondiente y excluir contactos internos antes de activar/usar la secuencia. | N8: Sigue mal — BNO reconoció que aplica | O8: No aplica | Q8: Filtrar por rol = 'Solicitante principal' antes de actualizar la propiedad. Validar que la secuencia también excluya dominios internos @monific.com. | S8: Master de Implementación_ Proceso Comercial - Monific | T8: Auditoría: Abierto; BNO validó por escrito que el hallazgo APLICA | U8: 2026-05-18 | V8: 46191 | W8: Sí
A9: CON-008 | B9: 1ª Auditoría (+ dictamen BNO) | C9: WF-003 · f8 | D9: Hallazgo base | F9: WF-003 | G9: Reinscripción apagada. Si un negocio retrocede a Nuevo (después de un rechazo temporal), no se re-pausa documentación ni se re-inscribe al contacto. Hay que ejecutar el ciclo a mano. | H9: Medio | I9: Medio | J9: Descartado | K9: Monific – Raquel | L9: Monific – negocio (Raquel) | M9: Validado por BNO. Se descarta para MVP por volumen actual y baja frecuencia esperada del caso. Mantener como mejora futura si aumentan reingresos o retrabajos en etapa Nuevo. | N9: Descartado por acuerdo de alcance (revisar) | O9: No aplica | Q9: Decidir con Comercial si re-procesar automáticamente al retroceso de etapa. Si sí, activar reinscripción. | S9: Master de Implementación_ Proceso Comercial - Monific | T9: Auditoría: Descartado (decisión de alcance/MVP) — revisar si Monific lo acepta | U9: 2026-05-18 | V9: 46191 | W9: No
A10: CON-009 | B10: 1ª Auditoría (+ dictamen BNO) | C10: WF-004 · f9 | D10: Hallazgo base | F10: WF-004 | G10: El WF está APAGADO. WF-003 marca la bandera para inscribir en secuencia de +15 días, pero como WF-004 está apagado, nadie ejecuta la inscripción. El ciclo de seguimiento al solicitante a 15 días queda roto. | H10: Alto | I10: Alto | J10: En curso | K10: BNO + Monific | L10: Compartido (BNO + Monific) | M10: Validado por BNO. En curso. La plantilla ya fue trabajada; queda pendiente validar aprobación final de contenido/remitente y activar WF-004 solo después de una prueba punta a punta con contacto de prueba. | N10: En curso (BNO) | O10: No aplica | Q10: Validar contenido del correo de la secuencia con Marketing/Comercial (asunto, body, opt-out, footer legal CNBV). Una vez aprobado, activar WF-004. | S10: Master de Implementación_ Proceso Comercial - Monific | T10: Auditoría/BNO: en curso, sin entregar | U10: 2026-05-18 | V10: 46191 | W10: Sí
A11: CON-010 | B11: 1ª Auditoría (+ dictamen BNO) | C11: WF-004 · f10 | D11: Hallazgo base | F11: WF-004 | G11: El nombre del WF en HubSpot es '...+15 días | V1' pero el master lo registra como 'Enviar secuencia desde contacto' (sin '+15 días'). Mismo tipo de desincronización en WF-021. Genera confusión | H11: Medio | I11: Medio | J11: Abierto | K11: BNO – Implementación | L11: BNO | M11: Validado por BNO. Aplica como limpieza de gobierno del proyecto. Se recomienda homologar el nombre del WF entre HubSpot y master para evitar confusión en soporte, auditoría y capacitación. | N11: Sigue mal — BNO reconoció que aplica | O11: No aplica | Q11: Decidir nomenclatura oficial y sincronizar. Recomendado: usar el nombre de HubSpot como fuente única y actualizar el master. | S11: Master de Implementación_ Proceso Comercial - Monific | T11: Auditoría: Abierto; BNO validó por escrito que el hallazgo APLICA | U11: 2026-05-18 | V11: 46191 | W11: Sí
A12: CON-011 | B12: 1ª Auditoría (+ dictamen BNO) | C12: WF-004 · f11 | D12: Hallazgo base | F12: WF-004 | G12: La inscripción a la secuencia se hace en nombre del 'Propietario del contacto'. Si el contacto no tiene propietario (caso común cuando entra por formulario), la inscripción falla. | H12: Medio | I12: Medio | J12: Abierto | K12: BNO – Implementación | L12: BNO | M12: Validado por BNO. Aplica parcialmente: la lógica de inscripción es correcta, pero requiere fallback de propietario/remitente. Definir si el remitente estándar será solicitantes@monific.com y ajustar antes de activar. | N12: Sigue mal — BNO reconoció que aplica | O12: No aplica | Q12: Agregar paso previo: si Propietario está vacío, asignar a solicitantes@monific.com (buzón compartido) y luego inscribir. | S12: Master de Implementación_ Proceso Comercial - Monific | T12: Auditoría: Abierto; BNO validó por escrito que el hallazgo APLICA | U12: 2026-05-18 | V12: 46191 | W12: Sí
A13: CON-012 | B13: 1ª Auditoría (+ dictamen BNO) | C13: WF-005 · f12 | D13: Hallazgo base | F13: WF-005 | G13: WF-002, WF-003 y WF-005 disparan todos en la misma etapa Nuevo. WF-003 y WF-005 se ejecutan en paralelo y setean banderas para secuencias distintas (+15d y +2d) sobre los mismos contactos → posible doble correo al solicitante. | H13: Alto | I13: Alto | J13: Abierto | K13: BNO – Implementación | L13: BNO | M13: Validado por BNO. Aplica como conflicto de diseño. Recomendamos consolidar el seguimiento de documentación en una sola lógica con delays internos o segmentar por antigüedad del negocio para evitar doble contacto. | N13: Sigue mal — BNO reconoció que aplica | O13: No aplica | Q13: Diferenciar con condiciones temporales: WF-005 con 'Negocio creado hace <2 días' y WF-003 con 'Negocio creado hace >=14 días'. O consolidar ambos en un solo WF con delays internos. | S13: Master de Implementación_ Proceso Comercial - Monific | T13: Auditoría: Abierto; BNO validó por escrito que el hallazgo APLICA | U13: 2026-05-18 | V13: 46191 | W13: Sí
... A113: CON-112 | B113: 1ª Auditoría (+ dictamen BNO) | C113: WF-062 · f112 | D113: Hallazgo base | F113: WF-062 | G113: PATRÓN SISTÉMICO en las 3 etapas terminales CNBV (Cierre Refi, Liquidada, Incumplimiento): los WFs de 'propiedades de entrada' son insuficientes. WF-062 solo setea 1 propiedad. WF-063 setea 4 propiedades trazables pero CERO notificaciones. WF-064 tiene notif pero solo a Raquel hardcoded. Las tres son reportables a CNBV y requieren: notificación consistente por rol, propiedades trazables completas, registro CNBV. La inconsistencia revela falta de template/SOP de cierre regulatorio. | H113: Crítico | I113: Crítico | J113: Abierto | K113: BNO + Monific | L113: Compartido (BNO + Monific) | M113: Validado por BNO. Aplica como patrón sistémico. Crear template/SOP único de cierre regulatorio CNBV para Refi, Liquidada e Incumplimiento con propiedades, notificaciones, registro y archivo. | N113: Sigue mal — BNO reconoció que aplica | O113: No aplica | Q113: Crear template canónico de 'Cierre regulatorio CNBV' que los 3 WFs adopten: (1) Propiedades completas (Historial pago, Estado crédito final, Monto recuperado, Fecha cierre); (2) Notificación por rol a Compliance + Dirección + Vian + Memo; (3) Registro CNBV trazable con todas las propiedades; (4) Tarea de archivo de expediente. WF-059 (Aprobación comité) puede inspirar. | S113: Master de Implementación Cobranza - Monific.xlsx | T113: Auditoría: Abierto; BNO validó por escrito que el hallazgo APLICA | U113: 2026-05-19 | V113: 46191 | W113: Sí
A114: CON-113 | B114: 2ª Auditoría | C114: BIT-001 | D114: Equipos | E114: Transversal | F114: Transversal | G114: ARI (FR/EM) quedó en el equipo "Legal" compartido con Compliance Monific (emiliano@monific.com), sin equipo dedicado. | H114: Crítico | I114: Crítico | J114: Abierto | K114: Compartido BNO+Monific | L114: Compartido (BNO + Monific) | N114: Sigue mal (abierto) | O114: No aplica | Q114: Crear equipo dedicado "Despacho Externo ARI" y separar a Compliance interno; revisar qué WFs/objetos notifican o comparten con "Legal". | R114: HubSpot Users&Teams: equipo "Legal" = Evelyn Montes (emontes@fulmentfi.com), FRANCISCO RODRIGUEZ (direccion@fulmentfi.com), Miguel Emiliano Chacon Lopez (emiliano@monific.com). | T114: Auditoría: Abierto | U114: 2026-06-08 00:00:00 | V114: 46191 | W114: Sí
A115: CON-114 | B115: 2ª Auditoría | C115: BIT-002 | D115: Nuevo ARI | E115: 02 Solicitante | F115: WF-016 / Solicitantes Etapa 03 Nº02 | G115: El WF "Notificación interna a involucrados" notifica al equipo "Legal" (donde hoy está ARI), exponiendo pipeline interno de Solicitantes a un despacho externo. | H115: Crítico | I115: Crítico | J115: Abierto | K115: Compartido BNO+Monific | L115: Compartido (BNO + Monific) | N115: Sigue mal (abierto) | O115: No aplica | Q115: Cambiar destinatario de "Legal" a "Evaluación Jurídica" (EEJ), que es el equipo que el master pretendía; excluir al equipo donde está ARI. | R115: Canvas flow 1808311603: "Enviar … a Marketing y Legal." Master declara "involucrados (EEJ y MKT)" (maestro fila 43). | T115: Auditoría: Abierto | U115: 2026-06-08 00:00:00 | V115: 46191 | W115: Sí
A116: CON-115 | B116: 2ª Auditoría | C116: BIT-004 | D116: Re-validación | E116: 05 Cobranza | F116: WF-050 / Cobranza Etapa 01 Nº01 | G116: WF de asignación de propietario sigue apuntando al equipo "Atención al Cliente" en vez del equipo "Cobranza". Sin cambio respecto a 1ª pasada. | H116: Crítico | I116: Crítico | J116: Sin cambio | K116: BNO – Implementación | L116: BNO | N116: Sigue mal (abierto) | O116: No aplica | Q116: Cambiar el target del round-robin al equipo "Cobranza". | R116: Canvas flow 1820379477: "Rotar … Asignar a Usuarios y equipos específicos → Atención al Cliente (2), Distribución Rotación". | T116: Auditoría: Sin cambio | U116: 2026-06-08 00:00:00 | V116: 46191 | W116: Sí
A117: CON-116 | B117: 2ª Auditoría | C117: BIT-011 | D117: Re-validación | E117: 02 Solicitante | F117: WF-008 | G117: Reinscripción desactivada: si el comité aprueba tras entrar a Evaluación (caso normal), el WF no dispara y el negocio se atora en Evaluación. | H117: Crítico | I117: Crítico | J117: Sin cambio | K117: BNO – Implementación | L117: BNO | N117: Sigue mal (abierto) | O117: No aplica | Q117: Activar reinscripción o cambiar trigger a 'Resolución de Comité cambia a Aprobado'. Probar en sandbox con decisión previa y posterior al ingreso. | R117: Flow 1807924876 'Etapa 02 Nº01 Cambio de etapa a Formalización'. Trigger: Pipeline Solicitantes + Etapa=Evaluación + Resolución de Comité=Aprobado, con 'Reinscripción desactivada' visible en canvas. | S117: Re-validación; actualiza fila 22.0 de la 1ª pasada | T117: Auditoría: Sin cambio | U117: 2026-06-09 00:00:00 | V117: 46191 | W117: Sí
A118: CON-117 | B118: 2ª Auditoría | C118: BIT-012 | D118: Re-validación | E118: 02 Solicitante | F118: WF-008 | G118: Al mover a Formalización no se escribe Fecha de cambio de etapa ni Origen del cambio. Sin trazabilidad CNBV de quién/qué movió el negocio. | H118: Crítico | I118: Crítico | J118: Sin cambio | K118: BNO – Implementación | L118: BNO | N118: Sigue mal (abierto) | O118: No aplica | Q118: Agregar acciones Editar registro: Fecha cambio etapa a Formalización y Origen=WF-008. Replicar en WF-009/015/018/022. | R118: Flow 1807924876. Única acción es '1. Editar registro' que define Pipeline y etapa=Formalización; no hay acción que escriba fecha de cambio ni origen. | S118: Re-validación; actualiza fila 23.0 de la 1ª pasada | T118: Auditoría: Sin cambio | U118: 2026-06-09 00:00:00 | V118: 46191 | W118: Sí
A119: CON-118 | B119: 2ª Auditoría | C119: BIT-014 | D119: Re-validación | E119: 02 Solicitante | F119: WF-009 | G119: Reinscripción desactivada en rechazos: si el comité rechaza tras entrar a Evaluación (caso normal), el WF no dispara y el negocio no pasa a Cierre Perdido. | H119: Crítico | I119: Crítico | J119: Sin cambio | K119: BNO – Implementación | L119: BNO | N119: Sigue mal (abierto) | O119: No aplica | Q119: Activar reinscripción o disparar por 'Resolución de Comité cambia a Rechazado'. | R119: Flow 1807927041 'Etapa 02 Nº02 Cambio de etapa a perdido'. Trigger: Evaluación + Resolución de Comité=Rechazado, 'Reinscripción desactivada' visible. | S119: Re-validación; actualiza fila 25.0 de la 1ª pasada | T119: Auditoría: Sin cambio | U119: 2026-06-09 00:00:00 | V119: 46191 | W119: Sí
A120: CON-119 | B120: 2ª Auditoría | C120: BIT-015 | D120: Re-validación | E120: 02 Solicitante | F120: WF-009 | G120: Al mover a Cierre Perdido no escribe Fecha de cambio de etapa ni Origen del cambio. Sin trazabilidad CNBV en rechazos. | H120: Crítico | I120: Crítico | J120: Sin cambio | K120: BNO – Implementación | L120: BNO | N120: Sigue mal (abierto) | O120: No aplica | Q120: Agregar acciones Editar registro: Fecha cambio etapa y Origen=WF-009. | R120: Flow 1807927041: única acción '1. Editar registro' define etapa=Cierre perdido; no escribe fecha de cambio ni origen. | S120: Re-validación; actualiza fila 26.0 de la 1ª pasada | T120: Auditoría: Sin cambio | U120: 2026-06-09 00:00:00 | V120: 46191 | W120: Sí
A121: CON-120 | B121: 2ª Auditoría | C121: BIT-016 | D121: Nuevo ARI | E121: 02 Solicitante | F121: WF-010 | G121: FUGA ARI adicional a BIT-002: la acción 1 envía notificación interna al equipo 'Legal', donde hoy está ARI (FR/EM). ARI recibe avisos del pipeline de Solicitantes en Evaluación. | H121: Crítico | I121: Crítico | J121: Abierto | K121: BNO – Implementación | L121: BNO | N121: Sigue mal (abierto) | O121: No aplica | Q121: Sacar a ARI de 'Legal' (equipo dedicado) o cambiar destinatario a equipo interno de Compliance. Mismo arreglo que BIT-002. | R121: Flow 1808160659 'Etapa 02 Nº03 Correo interno a involucrados'. Acción 1: 'Enviar notificación interna por correo... a Legal'. Equipo Legal contiene a ARI (Fulmentfi). | T121: Auditoría: Abierto | U121: 2026-06-09 00:00:00 | V121: 46191 | W121: Sí
A122: CON-121 | B122: 2ª Auditoría | C122: BIT-017 | D122: Re-validación | E122: 02 Solicitante | F122: WF-010 | G122: Acción 4 'Enviar correo Notificacion al DG' va a 'Todos los contactos asociados', lo que incluye al solicitante. Filtración de comunicación interna al cliente. | H122: Crítico | I122: Crítico | J122: Sin cambio | K122: BNO – Implementación | L122: BNO | N122: Sigue mal (abierto) | O122: No aplica | Q122: Cambiar destinatario a un usuario/rol interno (DG) en vez de 'Todos los contactos asociados'. Es notificación interna, no debe ir al cliente. | R122: Flow 1808160659, acción 4: 'Enviar Notificacion al DG de avance de solicitante a los contactos asociados con la etiqueta Todos los contactos asociados'. | S122: Re-validación; actualiza fila 27.0 de la 1ª pasada | T122: Auditoría: Sin cambio | U122: 2026-06-09 00:00:00 | V122: 46191 | W122: Sí
A123: CON-122 | B123: 2ª Auditoría | C123: BIT-020 | D123: Re-validación | E123: 02 Solicitante | F123: WF-012 | G123: Trigger solo dispara si Resolución=Aprobado y reinscripción desactivada. En rechazos o si la decisión se setea tras el ingreso, la Fecha de decisión nunca se registra. Rompe SLA/trazabilidad. | H123: Crítico | I123: Crítico | J123: Sin cambio | K123: BNO – Implementación | L123: BNO | N123: Sigue mal (abierto) | O123: No aplica | Q123: Disparar por 'Resolución de Comité cambia' (Aprobado o Rechazado) y activar reinscripción, para registrar fecha en todos los casos. | R123: Flow 1807992844 'Etapa 02 Nº05 fijar Fecha de decisión del comité'. Trigger: Evaluación + Resolución=Aprobado, 'Reinscripción desactivada'. Acción: define fecha=fecha de ejecución. | S123: Re-validación; actualiza fila 32.0 de la 1ª pasada | T123: Auditoría: Sin cambio | U123: 2026-06-09 00:00:00 | V123: 46191 | W123: Sí
A124: CON-123 | B124: 2ª Auditoría | C124: BIT-021 | D124: Re-validación | E124: 02 Solicitante | F124: WF-013 | G124: Trigger solo Resolución=Aprobado con reinscripción desactivada. Si la decisión se setea tras el ingreso a Evaluación, la tarea de carta de aceptación nunca se crea. | H124: Crítico | I124: Crítico | J124: Sin cambio | K124: BNO – Implementación | L124: BNO | N124: Sigue mal (abierto) | O124: No aplica | Q124: Disparar por cambio de propiedad Resolución=Aprobado y activar reinscripción. | R124: Flow 1807930283 'Etapa 02 Nº06 Crear tarea carta de aceptación'. Trigger: Evaluación + Resolución=Aprobado, 'Reinscripción desactivada'. | S124: Re-validación; actualiza fila 35.0 de la 1ª pasada | T124: Auditoría: Sin cambio | U124: 2026-06-09 00:00:00 | V124: 46191 | W124: Sí
A125: CON-124 | B125: 2ª Auditoría | C125: BIT-023 | D125: Re-validación | E125: 02 Solicitante | F125: WF-014 | G125: WF DESACTIVADO en HubSpot (master dice 'Encendido'). Las solicitudes rechazadas no generan tarea de carta de rechazo; el solicitante nunca recibe notificación formal. | H125: Crítico | I125: Crítico | J125: Sin cambio | K125: BNO – Implementación | L125: BNO | N125: Sigue mal (abierto) | O125: No aplica | Q125: Decidir si debe activarse; si sí, corregir trigger (cambio de propiedad) y reinscripción antes de activar. Alinear con master. | R125: Flow 1808048197 'Etapa 02 Nº07 Crear tarea carta de rechazo'. Badge 'DESACTIVADA'; botón 'Revisar y activar'. Trigger: Evaluación + Resolución=Rechazado. | S125: Re-validación; actualiza fila 38.0 de la 1ª pasada | T125: Auditoría: Sin cambio | U125: 2026-06-09 00:00:00 | V125: 46191 | W125: Sí
A126: CON-125 | B126: 2ª Auditoría | C126: BIT-024 | D126: Re-validación | E126: 02 Solicitante | F126: WF-015 | G126: Pasa a Proceso de firma sin escribir Fecha de cambio etapa ni Origen; reinscripción desactivada (si Estatus=Liquidada se setea en la etapa, el WF no dispara). Etapa crítica de firma. | H126: Crítico | I126: Crítico | J126: Sin cambio | K126: BNO – Implementación | L126: BNO | N126: Sigue mal (abierto) | O126: No aplica | Q126: Agregar escritura de Fecha cambio etapa + Origen=WF-015 y disparar por cambio de propiedad; activar reinscripción. | R126: Flow 1808166282 'Etapa 03 Nº01 Cambio a proceso de firma'. Trigger: Formalización + Estatus de formalización=Liquidada, 'Reinscripción desactivada'. Única acción: edita etapa. | S126: Re-validación; actualiza fila 41.0 de la 1ª pasada | T126: Auditoría: Sin cambio | U126: 2026-06-09 00:00:00 | V126: 46191 | W126: Sí
A127: CON-126 | B127: 2ª Auditoría | C127: BIT-026 | D127: Nuevo ARI | E127: 02 Solicitante | F127: WF-016 / Solicitantes Etapa 03 Nº02 | G127: Ampliación de BIT-002: confirmado en canvas que la única acción notifica 'a Marketing y Legal'. ARI (en equipo Legal) sigue recibiendo el aviso de inicio de gestiones. No duplicar BIT-002. | H127: Crítico | I127: Crítico | J127: Sin cambio | K127: BNO – Implementación | L127: BNO | N127: Sigue mal (abierto) | O127: No aplica | Q127: Mismo arreglo que BIT-002: sacar a ARI de 'Legal' o redirigir a equipo interno. Decidir corte inmediato vs esperar arreglo BNO. | R127: Flow 1808311603 'Etapa 03 Nº02 Notificación interna a involucrados'. Acción 1: 'Enviar Inicio de gestiones internas... a Marketing y Legal'. Confirma BIT-002. | T127: Auditoría: Sin cambio | U127: 2026-06-09 00:00:00 | V127: 46191 | W127: Sí
A128: CON-127 | B128: 2ª Auditoría | C128: BIT-027 | D128: Re-validación | E128: 02 Solicitante | F128: WF-017 | G128: El escalamiento por formalización estancada (>2 días) se envía al mismo 'Propietario del negocio' que está estancado, no a un superior. El escalamiento no cumple su propósito. | H128: Crítico | I128: Crítico | J128: Sin cambio | K128: BNO – Implementación | L128: BNO | N128: Sigue mal (abierto) | O128: No aplica | Q128: Redirigir escalamiento a rol superior (jefe de Formalización), no al propietario estancado. | R128: Flow 1808313453 'Etapa 03 Nº03 Notificación interna a superior estancado'. Acción 1: 'Atender escalamiento por formalización pendiente a Propietario del negocio'. | S128: Re-validación; actualiza fila 46.0 de la 1ª pasada | T128: Auditoría: Sin cambio | U128: 2026-06-09 00:00:00 | V128: 46191 | W128: Sí
A129: CON-128 | B129: 2ª Auditoría | C129: BIT-030 | D129: Re-validación | E129: 02 Solicitante | F129: WF-018 | G129: Al pasar a Cierre Ganado no escribe Fecha de cambio de etapa ni Origen. Mismo gap de trazabilidad CNBV que WF-008/009/015. WF-018 no estaba auditado en el maestro. | H129: Crítico | I129: Crítico | J129: Abierto | K129: BNO – Implementación | L129: BNO | N129: Sigue mal (abierto) | O129: No aplica | Q129: Agregar Editar registro: Fecha cambio etapa a Ganado y Origen=WF-018. | R129: Flow 1808711272: acciones son '1. Editar registro' (etapa a Ganado) y '2. notificación'. Ninguna escribe Fecha de cambio ni Origen. | T129: Auditoría: Abierto | U129: 2026-06-09 00:00:00 | V129: 46191 | W129: Sí
A130: CON-129 | B130: 2ª Auditoría | C130: BIT-032 | D130: Re-validación | E130: 02 Solicitante | F130: WF-020 | G130: WF DESACTIVADO (master lo marca 'Implementado'). La cadena WF-019->WF-020 queda rota: se setea la bandera pero la secuencia de firma nunca se envía al solicitante. | H130: Crítico | I130: Crítico | J130: Sin cambio | K130: Monific – Raquel | L130: Monific – negocio (Raquel) | N130: Sigue mal (abierto) | O130: No aplica | Q130: Validar el correo de la secuencia y activar el WF. Decisión de Raquel sobre contenido. | R130: Flow 1808682771 'Etapa 04 Nº03 Enviar secuencia'. Badge 'DESACTIVADA'. Trigger: contactos con 'Inscribir en secuencia de firma=Sí'; inscribe en secuencia 'WF - Notificar aprobación de credito firma'. | S130: Re-validación; actualiza fila 51.0 de la 1ª pasada | T130: Auditoría: Sin cambio | U130: 2026-06-09 00:00:00 | V130: 46191 | W130: No
A131: CON-130 | B131: 2ª Auditoría | C131: BIT-035 | D131: Re-validación | E131: 02 Solicitante | F131: WF-022 | G131: Mueve a Cierre Perdido sin setear 'Razón de cierre perdido', sin crear tarea para documentar/subir carta, y sin Fecha de cambio etapa ni Origen. | H131: Crítico | I131: Crítico | J131: Sin cambio | K131: BNO – Implementación | L131: BNO | N131: Sigue mal (abierto) | O131: No aplica | Q131: Agregar: setear Razón de cierre perdido, crear tarea de documentación y escribir Fecha cambio etapa + Origen=WF-022. | R131: Flow 1808890501: única acción '1. Editar registro' define etapa=Cierre perdido; sin razón de cierre, sin tarea, sin fecha/origen. | S131: Re-validación; actualiza fila 54.0 de la 1ª pasada | T131: Auditoría: Sin cambio | U131: 2026-06-09 00:00:00 | V131: 46191 | W131: Sí
A132: CON-131 | B132: 2ª Auditoría | C132: BIT-037 | D132: Re-validación | E132: 02 Solicitante | F132: WF-024 | G132: BUG CONFIRMADO: el WF 'Establecer propiedades de perdido' tiene trigger Etapa=Cierre GANADO (debería ser Perdido). Además define Fecha de cierre. Se dispara en ganados, no en perdidos. | H132: Crítico | I132: Crítico | J132: Sin cambio | K132: BNO – Implementación | L132: BNO | N132: Sigue mal (abierto) | O132: No aplica | Q132: Corregir trigger a Etapa=Cierre perdido y revisar que las propiedades correspondan a perdido (no Fecha de cierre). | R132: Flow 1808747845 'Etapa 06: Perdido Nº01 Establecer propiedades de perdido'. Trigger: 'Etapa del negocio es cualquiera de Cierre ganado'. Acción 1 define Fecha de cierre. | S132: Re-validación; actualiza fila 56.0 de la 1ª pasada | T132: Auditoría: Sin cambio | U132: 2026-06-09 00:00:00 | V132: 46191 | W132: Sí
A133: CON-132 | B133: 2ª Auditoría | C133: BIT-041 | D133: Re-validación | E133: 01 Inversionista | F133: WF-026 | G133: BUG copy-paste de WF-025: el flow 'Cambio de etapa a congelado' en realidad mueve el negocio a Inversionista Activo. Nunca congela. | H133: Crítico | I133: Crítico | J133: Sin cambio | K133: BNO – Implementación | L133: BNO | N133: Sigue mal (abierto) | O133: No aplica | Q133: Corregir acción para que defina la etapa como Congelado, no Activo. | R133: Flow 1808819073 'Perfil Nº02 Cambio de etapa a congelado'. Trigger: Perfil Activo + >15 días. Acción '1. Editar registro: Define etapa como Inversionista Activo' (debería ser Congelado). | T133: Auditoría: Sin cambio | U133: 2026-06-09 00:00:00 | V133: 46191 | W133: Sí
A134: CON-133 | B134: 2ª Auditoría | C134: BIT-042 | D134: Re-validación | E134: 01 Inversionista | F134: WF-027 | G134: CLABE STP hardcodeada al literal '1'. El dato financiero (CLABE 18 dígitos de STP) debe venir de Admin.Monific, no fijarse en 1. | H134: Crítico | I134: Crítico | J134: Sin cambio | K134: Monific – Tech (Jesús) | L134: Monific – TI | N134: Sigue mal (abierto) | O134: No aplica | Q134: Reemplazar el valor fijo por integración que traiga la CLABE STP real del inversionista desde Admin.Monific. | R134: Flow 1808747892 'Perfil Nº03 Actualizar propiedades de negocio'. Acción '2. Editar registro: Define CLABE STP como 1'. | T134: Auditoría: Sin cambio | U134: 2026-06-09 00:00:00 | V134: 46191 | W134: No
A135: CON-134 | B135: 2ª Auditoría | C135: BIT-051 | D135: Re-validación | E135: 01 Inversionista | F135: WF-033 | G135: Monto de primera inversión hardcodeado a 0. Dato financiero clave queda en cero fijo, no toma el monto real invertido. Riesgo CNBV de integridad de datos. | H135: Crítico | I135: Crítico | J135: Sin cambio | K135: Monific – Tech (Jesús) | L135: Monific – TI | N135: Sigue mal (abierto) | O135: No aplica | Q135: Tomar el monto real de la primera inversión desde Admin.Monific en vez de fijar 0. | R135: Flow 1808890885. Acción '2. Editar registro: Define Monto de primera inversión como 0'. | T135: Auditoría: Sin cambio | U135: 2026-06-09 00:00:00 | V135: 46191 | W135: No
A136: CON-135 | B136: 2ª Auditoría | C136: BIT-053 | D136: Re-validación | E136: 01 Inversionista | F136: WF-034 | G136: Tokens sin resolver: la acción de inscribir en secuencia usa {{ sequenceId }} y {{ senderType }} literales. HubSpot marca 'Se necesitan cambios'. El flow nunca funcionará. | H136: Crítico | I136: Crítico | J136: Sin cambio | K136: Monific – Tech (Jesús) | L136: Monific – TI | N136: Sigue mal (abierto) | O136: No aplica | Q136: Configurar secuencia real y remitente; eliminar tokens sin resolver. | R136: Flow 1808851292 'Activo Nº04 Realizar envio de secuencia'. Nodo '1. Inscribirse en una secuencia: Se necesitan cambios - Inscribir al contacto en {{ sequenceId }} de {{ senderType }}'. | T136: Auditoría: Sin cambio | U136: 2026-06-09 00:00:00 | V136: 46191 | W136: No
A137: CON-136 | B137: 2ª Auditoría | C137: BIT-059 | D137: Re-validación | E137: 01 Inversionista | F137: WF-039 | G137: BUG: en vez de notificar el cierre, el flow REGRESA el negocio de Cierre a Inversionista Activo (define etapa 1341314730). Corrompe el journey y no envía ninguna notificación. | H137: Crítico | I137: Crítico | J137: Sin cambio | K137: BNO – Implementación | L137: BNO | N137: Sigue mal (abierto) | O137: No aplica | Q137: Reemplazar la acción de cambio de etapa por la notificación interna prevista; no revertir el cierre. | R137: Flow 1808890376 'Cierre Nº01 Notificaciones internas'. Trigger Etapa=1341314732 (Cierre). Acción '1. Editar registro: define etapa como 1341314730' (= Inversionista Activo). | T137: Auditoría: Sin cambio | U137: 2026-06-09 00:00:00 | V137: 46191 | W137: Sí
A138: CON-137 | B138: 2ª Auditoría | C138: BIT-070 | D138: Re-validación | E138: 04 ATC | F138: WF-045 | G138: WF sigue DESACTIVADO y sin acciones (Trigger -> Fin). No crea la tarea automatica Tipo C a Guillermo con SLA que pide la minuta marzo 2026. | H138: Crítico | I138: Crítico | J138: Sin cambio | K138: BNO – Implementación | L138: BNO | N138: Sigue mal (abierto) | O138: No aplica | Q138: Construir accion: crear tarea a Guillermo con SLA (1h) y setear Fecha escalamiento Tipo C; luego activar el WF. | R138: Flow ID 1822136840. DESACTIVADA (boton 'Revisar y activar'). Trigger Grupo 1: Estado del ticket = En atencion (Servicio al Cliente) Y Tipo de ticket = Solicitante. Cuerpo: ninguna accion, va directo a 'Fin'. | S138: Re-validación; actualiza fila 96 de la 1ª pasada | T138: Auditoría: Sin cambio | U138: 2026-06-09 | V138: 46191 | W138: Sí
A139: CON-138 | B139: 2ª Auditoría | C139: BIT-076 | D139: Re-validación | E139: 04 ATC | F139: WF-049 | G139: El cierre dispara solo con Estado=Cerrado, sin validacion previa (confirmacion de cliente, nota de resolucion ni validacion de superior). Cualquier cierre manual lo activa. | H139: Crítico | I139: Crítico | J139: Sin cambio | K139: BNO – Implementación | L139: BNO | N139: Sigue mal (abierto) | O139: No aplica | Q139: Agregar condiciones de cierre valido (nota de resolucion obligatoria, confirmacion de cliente) antes de permitir el cierre. | R139: Flow ID 1822136625. Trigger Grupo 1 unica condicion: 'Estado del ticket es cualquiera de Cerrado (Servicio al Cliente)'. Accion 1: Define Fecha de cierre = fecha de ejecucion. WF Activado. | S139: Re-validación; actualiza fila 100 de la 1ª pasada | T139: Auditoría: Sin cambio | U139: 2026-06-09 | V139: 46191 | W139: Sí
A140: CON-139 | B140: 2ª Auditoría | C140: BIT-077 | D140: Re-validación | E140: 04 ATC | F140: WF-049 | G140: Rama Tipo E (Reclamacion formal UNE) NO setea la propiedad 'Proceso UNE Activo = Si'. El proceso UNE no queda marcado en el sistema. | H140: Crítico | I140: Crítico | J140: Sin cambio | K140: BNO – Implementación | L140: BNO | N140: Sigue mal (abierto) | O140: No aplica | Q140: Agregar en rama Tipo E una accion que setee 'Proceso UNE Activo = Si'. | R140: Flow ID 1822136625. Nodo '2. Ramificacion': 'Ve a Tipo E si se cumplen estos criterios: Tipo de ticket es Reclamacion formal UNE'. La rama Tipo E solo tiene la accion 3 (correo); no hay nodo Editar registro que setee 'Proceso UNE Activo'. | S140: Re-validación; actualiza fila 100 de la 1ª pasada | T140: Auditoría: Sin cambio | U140: 2026-06-09 | V140: 46191 | W140: Sí
A141: CON-140 | B141: 2ª Auditoría | C141: BIT-078 | D141: Re-validación | E141: 04 ATC | F141: WF-049 | G141: Rama Tipo E NO crea expediente espejo en el pipeline UNE. La reclamacion CNBV no genera registro formal en el pipeline UNE. | H141: Crítico | I141: Crítico | J141: Sin cambio | K141: BNO – Implementación | L141: BNO | N141: Sigue mal (abierto) | O141: No aplica | Q141: Agregar accion que cree el expediente espejo en el pipeline UNE al detectar Tipo E. | R141: Flow ID 1822136625. Rama Tipo E del nodo Ramificacion solo ejecuta '3. Enviar notificacion interna por correo' y termina en End. No hay accion de crear registro/ticket en pipeline UNE. | S141: Re-validación; actualiza fila 100 de la 1ª pasada | T141: Auditoría: Sin cambio | U141: 2026-06-09 | V141: 46191 | W141: Sí
A142: CON-141 | B142: 2ª Auditoría | C142: BIT-079 | D142: Re-validación | E142: 04 ATC | F142: WF-049 | G142: Rama Tipo E NO genera folio UNE con formato CNBV. La reclamacion formal no obtiene identificador regulatorio. | H142: Crítico | I142: Crítico | J142: Sin cambio | K142: Compartido BNO+Monific | L142: Compartido (BNO + Monific) | N142: Sigue mal (abierto) | O142: No aplica | Q142: Agregar generacion de folio UNE con formato CNBV (prefijo + consecutivo) en la rama Tipo E. Generacion tecnica la coordina Monific-Tech (Jesus). | R142: Flow ID 1822136625. Rama Tipo E unicamente envia correo 'REGISTRO UNE: Tipo E | Ticket #'. No hay accion que genere ni setee un folio UNE con formato CNBV. | S142: Re-validación; actualiza fila 100 de la 1ª pasada | T142: Auditoría: Sin cambio | U142: 2026-06-09 | V142: 46191 | W142: Sí
A143: CON-142 | B143: 2ª Auditoría | C143: BIT-080 | D143: Re-validación | E143: 04 ATC | F143: WF-049 | G143: La notificacion de la rama Tipo E (UNE) va solo a 'Raquel Alfie' hardcoded; NO notifica a Compliance (emiliano@monific.com) ni a Direccion. | H143: Crítico | I143: Crítico | J143: Sin cambio | K143: BNO – Implementación | L143: BNO | N143: Sigue mal (abierto) | O143: No aplica | Q143: Notificar a Compliance + Direccion + responsable UNE por rol/equipo; quitar usuario hardcoded. | R143: Flow ID 1822136625. Accion '3. Enviar notificacion interna por correo': "Enviar REGISTRO UNE: Tipo E | Ticket # [Nombre del ticket] a Raquel Alfie". Unico destinatario. | S143: Re-validación; actualiza fila 101 de la 1ª pasada | T143: Auditoría: Sin cambio | U143: 2026-06-09 | V143: 46191 | W143: Sí
A144: CON-143 | B144: 2ª Auditoría | C144: BIT-081 | D144: Nuevo cambio modelo BNO-TI | E144: 04 ATC | F144: WF-049 | G144: WF-049 no bloquea el cierre del ticket Servicio hasta documentar el UNE: el ticket ya esta Cerrado cuando dispara y la rama Tipo E solo envia correo. | H144: Crítico | I144: Crítico | J144: Abierto | K144: Compartido BNO+Monific | L144: Compartido (BNO + Monific) | N144: Sigue mal (abierto) | O144: No aplica | Q144: Impedir cierre del ticket Servicio mientras 'Proceso UNE Activo = Si' y el expediente UNE no este documentado (bloqueo/regreso de etapa). | R144: Flow ID 1822136625. Trigger es Estado=Cerrado (el cierre ya ocurrio). Rama Tipo E: solo correo -> End. No hay gate ni reversion de etapa mientras UNE no este documentado. | T144: Auditoría: Abierto | U144: 2026-06-09 | V144: 46191 | W144: Sí
A145: CON-144 | B145: 2ª Auditoría | C145: BIT-082 | D145: Otro | E145: 04 ATC | F145: WF-049 | G145: Existe pipeline UNE construido con su propio WF (incluye generacion de Folio UNE) pero esta DESACTIVADO con 0 inscritos; y WF-049 no lo alimenta. El flujo UNE esta inoperante de punta a punta. | H145: Crítico | I145: Crítico | J145: Bloqueado | K145: Compartido BNO+Monific | L145: Compartido (BNO + Monific) | N145: Bloqueado — pendiente decisión Monific | O145: No aplica | Q145: Activar el WF del pipeline UNE y conectar WF-049 para que cree el expediente en pipeline UNE; validar folio CNBV. Coordinacion BNO (construccion) + Monific-Tech (Jesus). | R145: Flow ID 1822147164 '04. Tickets | 03. UNE | Etapa 01: Abierto | N01 | Propiedades de entrada': DESACTIVADA, 0 inscritos. Trigger Estado=Abierto (UNE). Accion 1 define Folio UNE como 'UNE - [Fecha de creacion]'. Ningun WF crea tickets en pipeline UNE (ver BIT-078). | T145: Auditoría: Bloqueado; BNO lo dejó a decisión de Monific | U145: 2026-06-09 | V145: 46191 | W145: Sí
A146: CON-145 | B146: 2ª Auditoría | C146: BIT-093 | D146: Otro | E146: 05 Cobranza | F146: WF-057 | G146: WF-057 transicion a Ejecucion de Garantia (Dia 61+) SOLO cambia de etapa: no notifica a Compliance/Direccion/Memo, no crea tarea juridica, no registra trazabilidad CNBV. | H146: Crítico | I146: Crítico | J146: Abierto | K146: BNO – Implementación | L146: BNO | N146: Sigue mal (abierto) | O146: No aplica | Q146: Agregar notificacion a Compliance/Direccion, tarea juridica y seteo de propiedades CNBV al entrar a Ejecucion de Garantia. | R146: Flow 1820915286. Trigger: Estado de ticket = Cobranza Activa Y Dias de mora >= 61. Accion unica: Editar registro -> estado Ejecucion de Garantia. Sin mas acciones. | T146: Auditoría: Abierto | U146: 2026-06-09 00:00:00 | V146: 46191 | W146: Sí
A147: CON-146 | B147: 2ª Auditoría | C147: BIT-094 | D147: Nuevo ARI | E147: 05 Cobranza | F147: WF-057 | G147: WF-057 mueve a Ejecucion de Garantia (Dia 61+) sin incorporar al despacho externo (ARI), que segun acuerdo es abogado externo por default en esta etapa. | H147: Crítico | I147: Crítico | J147: Abierto | K147: Despacho externo (ARI) | L147: Despacho externo (ARI) | N147: Sigue mal (abierto) | O147: No aplica | Q147: Asignar a ARI (futuro equipo 'Despacho externo') la responsabilidad juridica al entrar a Ejecucion de Garantia, via tarea y notificacion. | R147: Flow 1820915286. La transicion a Ejecucion de Garantia no genera ninguna asignacion ni notificacion al despacho (ARI). | T147: Auditoría: Abierto | U147: 2026-06-09 00:00:00 | V147: 46191 | W147: No
A148: CON-147 | B148: 2ª Auditoría | C148: BIT-099 | D148: Nuevo ARI | E148: 05 Cobranza | F148: WF-060 | G148: WF-060 mueve a Ejecucion de Garantia (rechazo de comite) sin notificar a Compliance/Direccion, sin crear tarea juridica y sin incorporar al despacho externo (ARI). | H148: Crítico | I148: Crítico | J148: Abierto | K148: Despacho externo (ARI) | L148: Despacho externo (ARI) | N148: Sigue mal (abierto) | O148: No aplica | Q148: Al rechazo de comite, notificar a Compliance/Direccion, crear tarea juridica y asignar a ARI como abogado externo por default. | R148: Flow 1820907946. Tras rechazo de comite el ticket pasa a Ejecucion de Garantia sin ninguna accion de notificacion ni asignacion juridica (ARI). | T148: Auditoría: Abierto | U148: 2026-06-09 00:00:00 | V148: 46191 | W148: No
A149: CON-148 | B149: 2ª Auditoría | C149: BIT-100 | D149: Re-validación | E149: 05 Cobranza | F149: WF-061 | G149: WF-061 (Ejecucion de Garantia) tiene hardcoded a Vianey/Raquel: notif accion 4 a Raquel Alfie y Vianey Correa; tareas 5 y 6 asignadas a Vianey Correa. | H149: Crítico | I149: Crítico | J149: Abierto | K149: BNO – Implementación | L149: BNO | N149: Sigue mal (abierto) | O149: No aplica | Q149: Reemplazar destinatarios y asignatarios fijos por equipo/rol (Cobranza, Direccion, Juridico). | R149: Flow 1820908035. Accion 4 'NOTIFICACION CRITICA: Inicio de Etapa de Ejecucion de Garantia' a Raquel Alfie y Vianey Correa. Accion 5 'Revision de Expediente' y accion 6 'Coordinar sesion de comite' asignadas a Vianey Correa. | T149: Auditoría: Abierto | U149: 2026-06-09 00:00:00 | V149: 46191 | W149: Sí
A150: CON-149 | B150: 2ª Auditoría | C150: BIT-101 | D150: Nuevo ARI | E150: 05 Cobranza | F150: WF-061 | G150: WF-061 no incluye al despacho externo (ARI) ni en la notificacion critica ni en las tareas juridicas (Revision de Expediente, Coordinar comite). ARI es abogado por default en Dia 61+. | H150: Crítico | I150: Crítico | J150: Abierto | K150: Despacho externo (ARI) | L150: Despacho externo (ARI) | N150: Sigue mal (abierto) | O150: No aplica | Q150: Incluir a ARI (equipo 'Despacho externo') como destinatario de la notificacion critica y asignatario de las tareas juridicas de Ejecucion de Garantia. | R150: Flow 1820908035. Destinatarios de notif y asignatarios de tareas: Raquel/Vianey. No aparece ARI ni el futuro equipo 'Despacho externo'. | T150: Auditoría: Abierto | U150: 2026-06-09 00:00:00 | V150: 46191 | W150: No
A151: CON-150 | B151: 2ª Auditoría | C151: BIT-102 | D151: Otro | E151: 05 Cobranza | F151: WF-061 | G151: WF-061 notif critica no incluye a Memo ni a Compliance. No setea propiedades regulatorias CNBV (Monto recuperado, Fecha reporte CNBV); solo Semaforo, Fecha de envio a garantia y Estatus juridico. | H151: Crítico | I151: Crítico | J151: Abierto | K151: Compartido BNO+Monific | L151: Compartido (BNO + Monific) | N151: Sigue mal (abierto) | O151: No aplica | Q151: Agregar Memo y Compliance a la notificacion y setear propiedades regulatorias CNBV de la etapa terminal. | R151: Flow 1820908035. Acciones 1-3: Semaforo=Critico, Fecha de envio a garantia, Estatus del proceso juridico=Iniciado. Sin propiedades CNBV (Monto recuperado, Fecha reporte CNBV) ni destinatarios Memo/Compliance. | T151: Auditoría: Abierto | U151: 2026-06-09 00:00:00 | V151: 46191 | W151: Sí
A152: CON-151 | B152: 2ª Auditoría | C152: BIT-103 | D152: Otro | E152: 05 Cobranza | F152: WF-062 | G152: WF-062 (Cierre por refinanciamiento, etapa terminal) solo setea 'Fecha de cierre'. No setea Estado credito final, Monto recuperado ni Fecha reporte CNBV; no notifica a Compliance. | H152: Crítico | I152: Crítico | J152: Abierto | K152: Compartido BNO+Monific | L152: Compartido (BNO + Monific) | N152: Sigue mal (abierto) | O152: No aplica | Q152: Setear propiedades regulatorias CNBV (Estado credito final, Monto recuperado, Fecha reporte CNBV) y notificar a Compliance al cerrar por refinanciamiento. | R152: Flow 1820906657. Trigger: Estado de ticket = Cierre por refinanciamiento. Accion unica: Editar registro -> Fecha de cierre = fecha de ejecucion. Estructura minima. | T152: Auditoría: Abierto | U152: 2026-06-09 00:00:00 | V152: 46191 | W152: Sí
A153: CON-152 | B153: 2ª Auditoría | C153: BIT-104 | D153: Re-validación | E153: 05 Cobranza | F153: WF-063 | G153: WF-063 (Campana Liquidada) setea 4 propiedades (Fecha liquidacion, Fecha cierre, Historial de pago=Limpio, Estado credito final=Activo) pero falta Monto recuperado y Fecha reporte CNBV; no notifica a Compliance. | H153: Crítico | I153: Crítico | J153: Abierto | K153: Compartido BNO+Monific | L153: Compartido (BNO + Monific) | N153: Sigue mal (abierto) | O153: No aplica | Q153: Agregar Monto recuperado y Fecha reporte CNBV, notificar a Compliance y generar reporte regulatorio de liquidacion. | R153: Flow 1822135185. Acciones: Fecha de liquidacion, Fecha de cierre, Historial de pago=Limpio, Estado de credito final=Activo. Sin Monto recuperado/Fecha reporte CNBV ni notif Compliance. | T153: Auditoría: Abierto | U153: 2026-06-09 00:00:00 | V153: 46191 | W153: Sí
A154: CON-153 | B154: 2ª Auditoría | C154: BIT-106 | D154: Re-validación | E154: 05 Cobranza | F154: WF-064 | G154: WF-064 (Cierre por Incumplimiento) NO setea Historial de pago = Sucio ni Estado de credito final = Incumplido. Solo setea fechas de cierre. Falta trazabilidad CNBV clave. | H154: Crítico | I154: Crítico | J154: Abierto | K154: BNO – Implementación | L154: BNO | N154: Sigue mal (abierto) | O154: No aplica | Q154: Agregar acciones Editar registro: Historial de pago = Sucio y Estado de credito final = Incumplido. | R154: Flow 1822086313. Acciones: 1) Fecha de cierre por incumplimiento, 2) Fecha de cierre, 3) Notif. Sin Historial=Sucio ni Estado de credito final=Incumplido. | T154: Auditoría: Abierto | U154: 2026-06-09 00:00:00 | V154: 46191 | W154: Sí
A155: CON-154 | B155: 2ª Auditoría | C155: BIT-107 | D155: Re-validación | E155: 05 Cobranza | F155: WF-064 | G155: WF-064 notif 'Cierre por Incumplimiento' va hardcoded solo a Raquel. No incluye Compliance, Memo ni al despacho externo (ARI) que llevo la ejecucion. | H155: Crítico | I155: Crítico | J155: Abierto | K155: BNO – Implementación | L155: BNO | N155: Sigue mal (abierto) | O155: No aplica | Q155: Reemplazar a Raquel por equipo/rol y agregar Compliance, Direccion y ARI como destinatarios del cierre por incumplimiento. | R155: Flow 1822086313, accion 3 'Enviar notificacion interna por correo': 'Notificacion de Cierre por Incumplimiento de Pago | Nombre del ticket' a Raquel. | T155: Auditoría: Abierto | U155: 2026-06-09 00:00:00 | V155: 46191 | W155: Sí
... A159: CON-158 | B159: 2ª Auditoría | C159: BIT-006 | D159: Re-validación | E159: 02 Solicitante | F159: WF-011 / Solicitantes Etapa 03 Nº03 (superior estancado) | G159: Escalamiento por formalización pendiente sigue yendo a "David Ochoa" (consultor BNO) hardcoded en vez de rol/equipo interno. | H159: Alto | I159: Alto | J159: Sin cambio | K159: BNO – Implementación | L159: BNO | N159: Sigue mal (abierto) | O159: No aplica | Q159: Parametrizar por rol/equipo interno (Dirección/Comité); no enrutar escalamientos operativos a un externo BNO. | R159: Canvas flow 1808313453 nodo 3: "Enviar Escalamiento por apoyo en formalización a David Ochoa." | T159: Auditoría: Sin cambio | U159: 2026-06-08 00:00:00 | V159: 46191 | W159: Sí
A160: CON-159 | B160: 2ª Auditoría | C160: BIT-013 | D160: Re-validación | E160: 02 Solicitante | F160: WF-008 | G160: Al pasar a Formalización no se notifica a nadie (asesor, solicitante ni equipo). El único paso es editar etapa y luego End. | H160: Alto | I160: Alto | J160: Sin cambio | K160: Compartido BNO+Monific | L160: Compartido (BNO + Monific) | N160: Sigue mal (abierto) | O160: No aplica | Q160: Encadenar notificación al equipo de Formalización (por rol, no usuario) al entrar a la etapa, o confirmar que WF-016 cubre este caso. | R160: Flow 1807924876: secuencia 'Editar registro' -> 'End'. Sin acción de notificación. WF-016 (notif) no está encadenado a este. | S160: Re-validación; actualiza fila 24.0 de la 1ª pasada | T160: Auditoría: Sin cambio | U160: 2026-06-09 00:00:00 | V160: 46191 | W160: Sí
A161: CON-160 | B161: 2ª Auditoría | C161: BIT-018 | D161: Re-validación | E161: 02 Solicitante | F161: WF-010 | G161: Acción 1 solo envía correo a Legal, pero acción 2 marca Áreas notificadas = Jurídica + Técnica + Financiera. Técnica y Financiera no se enteran realmente. | H161: Alto | I161: Alto | J161: Sin cambio | K161: BNO – Implementación | L161: BNO | N161: Sigue mal (abierto) | O161: No aplica | Q161: Enviar correo a las 3 áreas o ajustar la propiedad para reflejar solo a quien se notificó realmente. | R161: Flow 1808160659: acción 1 'a Legal'; acción 2 'Define Áreas de evaluación notificadas como Área Jurídica, Área Técnica y Área Financiera'. | S161: Re-validación; actualiza fila 28.0 de la 1ª pasada | T161: Auditoría: Sin cambio | U161: 2026-06-09 00:00:00 | V161: 46191 | W161: Sí
A162: CON-161 | B162: 2ª Auditoría | C162: BIT-019 | D162: Equipos | E162: 02 Solicitante | F162: WF-011 / Solicitantes Etapa 03 Nº03 (superior estancado) | G162: Notificación al DG hardcodeada al usuario 'David Ochoa' (nombre propio) en lugar de equipo/rol. Incumple compromiso BNO de WFs por equipos. | H162: Alto | I162: Alto | J162: Sin cambio | K162: BNO – Implementación | L162: BNO | N162: Sigue mal (abierto) | O162: No aplica | Q162: Reemplazar destinatario por equipo/rol 'Dirección General' para que no dependa de una persona. | R162: Flow 1807927091 'Etapa 02 Nº04 Correo interno a DG'. Acción 1: 'Enviar Nuevo solicitante enviado a evaluación a David Ochoa'. | S162: Re-validación; actualiza fila 29.0 de la 1ª pasada | T162: Auditoría: Sin cambio | U162: 2026-06-09 00:00:00 | V162: 46191 | W162: Sí
A163: CON-162 | B163: 2ª Auditoría | C163: BIT-022 | D163: Re-validación | E163: 02 Solicitante | F163: WF-013 | G163: Tarea asignada a 'Propietario del negocio' sin fallback si está vacío (queda huérfana). Además no se ve SLA/fecha de vencimiento ni escalamiento. | H163: Alto | I163: Alto | J163: Sin cambio | K163: BNO – Implementación | L163: BNO | N163: Sigue mal (abierto) | O163: No aplica | Q163: Agregar fallback de propietario y SLA (5 días + recordatorio día 3 + escalamiento). | R163: Flow 1807930283, acción 1: 'Crear tarea Enviar carta de aceptación ... asignarla a Propietario del negocio'. Sin vencimiento visible. | S163: Re-validación; actualiza fila 36.0 de la 1ª pasada | T163: Auditoría: Sin cambio | U163: 2026-06-09 00:00:00 | V163: 46191 | W163: Sí
A164: CON-163 | B164: 2ª Auditoría | C164: BIT-025 | D164: Re-validación | E164: 02 Solicitante | F164: WF-015 | G164: Al pasar a Proceso de firma no se notifica al solicitante con instrucciones de firma. WF-019/020 deberían cubrirlo pero WF-020 está apagado (ver BIT de WF-020). | H164: Alto | I164: Alto | J164: Sin cambio | K164: Compartido BNO+Monific | L164: Compartido (BNO + Monific) | N164: Sigue mal (abierto) | O164: No aplica | Q164: Asegurar encadenamiento con WF-019/020 (firma) y activar WF-020. | R164: Flow 1808166282: única acción edita etapa y End; sin notificación al solicitante. | S164: Re-validación; actualiza fila 43.0 de la 1ª pasada | T164: Auditoría: Sin cambio | U164: 2026-06-09 00:00:00 | V164: 46191 | W164: Sí
A165: CON-164 | B165: 2ª Auditoría | C165: BIT-028 | D165: Equipos | E165: 02 Solicitante | F165: WF-017 | G165: La acción 3 'Escalamiento por apoyo en formalización' está hardcodeada al usuario 'David Ochoa' en lugar de un rol/equipo superior. Incumple WFs por equipos. | H165: Alto | I165: Alto | J165: Abierto | K165: BNO – Implementación | L165: BNO | N165: Sigue mal (abierto) | O165: No aplica | Q165: Reemplazar 'David Ochoa' por equipo/rol superior de Formalización. | R165: Flow 1808313453, acción 3: 'Enviar Escalamiento por apoyo en formalización a David Ochoa'. | T165: Auditoría: Abierto | U165: 2026-06-09 00:00:00 | V165: 46191 | W165: Sí
A166: CON-165 | B166: 2ª Auditoría | C166: BIT-031 | D166: Re-validación | E166: 02 Solicitante | F166: WF-019 | G166: Setea 'Inscribir en secuencia de firma=Sí' en TODOS los contactos asociados, sin filtrar por rol. Contactos internos podrían recibir la secuencia comercial. | H166: Alto | I166: Alto | J166: Sin cambio | K166: BNO – Implementación | L166: BNO | N166: Sigue mal (abierto) | O166: No aplica | Q166: Filtrar por rol de contacto (solo solicitante/firmante) antes de setear la bandera. | R166: Flow 1808890551 'Etapa 04 Nº02 Editar campo para secuencia'. Acción 1: 'Define como Sí la propiedad Inscribir en secuencia de firma de los objetos asociados del tipo contactos'. | S166: Re-validación; actualiza fila 49.0 de la 1ª pasada | T166: Auditoría: Sin cambio | U166: 2026-06-09 00:00:00 | V166: 46191 | W166: Sí
A167: CON-166 | B167: 2ª Auditoría | C167: BIT-033 | D167: Re-validación | E167: 02 Solicitante | F167: WF-021 | G167: Las notificaciones de firma pendiente (>5 días) se envían al mismo 'Propietario del negocio' estancado, sin escalamiento a un superior. | H167: Alto | I167: Alto | J167: Sin cambio | K167: BNO – Implementación | L167: BNO | N167: Sigue mal (abierto) | O167: No aplica | Q167: Agregar escalamiento a rol superior tras N recordatorios sin avance. | R167: Flow 1808816250 'Etapa 04 Nº04 Notificaciones a asesor asignado'. Trigger: Proceso de firma + Tiempo en etapa>5 días. Acción 1 'Seguimiento al proceso de firma a Propietario del negocio'; acción 2 Retraso 5 días; acción 3 otra notificación. | S167: Re-validación; actualiza fila 52.0 de la 1ª pasada | T167: Auditoría: Sin cambio | U167: 2026-06-09 00:00:00 | V167: 46191 | W167: Sí
A168: CON-167 | B168: 2ª Auditoría | C168: BIT-038 | D168: Re-validación | E168: 02 Solicitante | F168: WF-024 | G168: La tarea 'Documentar motivo de negocio perdido' se asigna al mismo Propietario del negocio (asesor), sin fallback ni SLA visible. | H168: Alto | I168: Alto | J168: Sin cambio | K168: BNO – Implementación | L168: BNO | N168: Sigue mal (abierto) | O168: No aplica | Q168: Agregar fallback de propietario y SLA; considerar asignar a rol que valide motivo de perdido. | R168: Flow 1808747845, acción 4: 'Crear tarea Documentar motivo de negocio perdido y asignarla a Propietario del negocio'. | S168: Re-validación; actualiza fila 57.0 de la 1ª pasada | T168: Auditoría: Sin cambio | U168: 2026-06-09 00:00:00 | V168: 46191 | W168: Sí
A169: CON-168 | B169: 2ª Auditoría | C169: BIT-039 | D169: Re-validación | E169: 01 Inversionista | F169: WF-025 a WF-040 | G169: Patrón H-065 vigente: 14 de 16 WFs Inversionistas siguen Desactivados; solo WF-029 y WF-030 Activados. Journey no operativo. | H169: Alto | I169: Alto | J169: Sin cambio | K169: BNO – Implementación | L169: BNO | N169: Sigue mal (abierto) | O169: No aplica | Q169: Activar journey solo tras corregir bugs, o documentar formalmente que no está en alcance productivo. | R169: Portal 48427391: 14/16 flows del bloque en Desactivado. Activados solo Perfil Nº05 (flow 1808890225) y Nº06 (1808890880). | T169: Auditoría: Sin cambio | U169: 2026-06-09 00:00:00 | V169: 46191 | W169: Sí
A170: CON-169 | B170: 2ª Auditoría | C170: BIT-043 | D170: Re-validación | E170: 01 Inversionista | F170: WF-027 | G170: Nivel de registro hardcodeado a 3 sin lógica condicional. Todo negocio en Perfil Activo recibe Nivel 3 fijo, sin validar etapa real de onboarding. | H170: Alto | I170: Alto | J170: Sin cambio | K170: Monific – Tech (Jesús) | L170: Monific – TI | N170: Sigue mal (abierto) | O170: No aplica | Q170: Condicionar Nivel de registro al estado real de onboarding/STP en vez de fijar 3. | R170: Flow 1808747892 'Perfil Nº03'. Acción '1. Editar registro: Define Nivel de registro como 3. Cuenta STP creada'. Mismo valor 3 también en WF-028. | T170: Auditoría: Sin cambio | U170: 2026-06-09 00:00:00 | V170: 46191 | W170: No
A171: CON-170 | B171: 2ª Auditoría | C171: BIT-044 | D171: Re-validación | E171: 01 Inversionista | F171: WF-028 | G171: Template WhatsApp inadecuado: usa 'auto_respuesta_no_disponible' (autoresponder) en 2 nodos, no un mensaje de activación de inversionista. | H171: Alto | I171: Alto | J171: Sin cambio | K171: BNO – Implementación | L171: BNO | N171: Sigue mal (abierto) | O171: No aplica | Q171: Sustituir por plantilla de WhatsApp correcta de bienvenida/activación de inversionista. | R171: Flow 1808892052 'Perfil Nº04 Notificar a cliente'. Nodos 4 y 6 'Enviar mensaje de WhatsApp: Enviar auto_respuesta_no_disponible'. | T171: Auditoría: Sin cambio | U171: 2026-06-09 00:00:00 | V171: 46191 | W171: Sí
A172: CON-171 | B172: 2ª Auditoría | C172: BIT-045 | D172: Otro | E172: 01 Inversionista | F172: WF-028 | G172: WhatsApp se envía a 'Contactos: Todos los asociados' del negocio, no solo al inversionista titular. Riesgo de fuga a co-titulares/terceros asociados. | H172: Alto | I172: Alto | J172: Abierto | K172: BNO – Implementación | L172: BNO | N172: Sigue mal (abierto) | O172: No aplica | Q172: Limitar el envío al contacto titular (rol inversionista), no a todos los asociados. | R172: Flow 1808892052. Nodos 4 y 6 destinatario 'Contactos: Todos los asociados'. | T172: Auditoría: Abierto | U172: 2026-06-09 00:00:00 | V172: 46191 | W172: Sí
A173: CON-172 | B173: 2ª Auditoría | C173: BIT-048 | D173: Re-validación | E173: 01 Inversionista | F173: WF-031 | G173: Trigger sin condición de negocio: todo negocio en Inversionista Activo pasa automáticamente a Cierre. Sin trazabilidad CNBV del cambio. En UI muestra nombre, no ID crudo. | H173: Alto | I173: Alto | J173: Sin cambio | K173: BNO – Implementación | L173: BNO | N173: Sigue mal (abierto) | O173: No aplica | Q173: Agregar condición de negocio que justifique el cierre y propiedades de trazabilidad CNBV. | R173: Flow 1808852539 'Activo Nº01 Cambio de etapa a cierre'. Trigger solo 'Etapa = Inversionista Activo' sin más condición. Acción '1. Editar registro: define etapa como Cierre'. | T173: Auditoría: Sin cambio | U173: 2026-06-09 00:00:00 | V173: 46191 | W173: Sí
A174: CON-173 | B174: 2ª Auditoría | C174: BIT-049 | D174: Re-validación | E174: 01 Inversionista | F174: WF-032 | G174: Trigger sin condición: todo negocio Activo se congela automáticamente. Con WF-036 (Congelado->Activo sin condición) puede generar loop Activo<->Congelado. Sin trazabilidad. | H174: Alto | I174: Alto | J174: Sin cambio | K174: BNO – Implementación | L174: BNO | N174: Sigue mal (abierto) | O174: No aplica | Q174: Agregar condición (ej. inactividad/incumplimiento) y trazabilidad; coordinar con WF-036 para evitar loop. | R174: Flow 1808890239 'Activo Nº02 Cambio de etapa a congelado'. Trigger solo 'Etapa = Inversionista Activo'. Acción define etapa como Congelado. | T174: Auditoría: Sin cambio | U174: 2026-06-09 00:00:00 | V174: 46191 | W174: Sí
A175: CON-174 | B175: 2ª Auditoría | C175: BIT-054 | D175: Re-validación | E175: 01 Inversionista | F175: WF-035 | G175: WF-035 duplica las acciones de WF-033 (Fecha primera inversión x2 + Monto=0 + retraso 3d). Dos flows distintos hacen lo mismo, incl. mismo Monto=0 hardcoded. | H175: Alto | I175: Alto | J175: Sin cambio | K175: BNO – Arquitectura | L175: BNO | N175: Sigue mal (abierto) | O175: No aplica | Q175: Consolidar WF-033 y WF-035 en un solo flow y corregir Monto=0. | R175: Flow 1808852554 'Activo Nº05 Actualizar datos de entrada en etapa'. Acciones idénticas a flow 1808890885 (WF-033): nodos 1 y 4 'Fecha primera inversión', nodo 2 'Monto=0'. Trigger aquí usa nombres. | T175: Auditoría: Sin cambio | U175: 2026-06-09 00:00:00 | V175: 46191 | W175: Sí
A176: CON-175 | B176: 2ª Auditoría | C176: BIT-055 | D176: Otro | E176: 01 Inversionista | F176: WF-036 | G176: Reactivación sin condición: todo negocio en Congelado vuelve automáticamente a Activo, anulando el congelamiento. Junto con WF-032 puede crear loop. Sin trazabilidad. | H176: Alto | I176: Alto | J176: Abierto | K176: BNO – Implementación | L176: BNO | N176: Sigue mal (abierto) | O176: No aplica | Q176: Agregar condición de reactivación (ej. resolución de incidencia) y trazabilidad; evitar loop con WF-032. | R176: Flow 1808815771 'Congelado Nº01 Cambio de etapa a activo'. Trigger solo 'Etapa = Congelado'. Acción define etapa como Inversionista Activo. Sin condición de reactivación. | T176: Auditoría: Abierto | U176: 2026-06-09 00:00:00 | V176: 46191 | W176: Sí
A177: CON-176 | B177: 2ª Auditoría | C177: BIT-058 | D177: Re-validación | E177: 01 Inversionista | F177: WF-038 | G177: Correo sin configurar ('Correo desconocido', Se necesitan cambios) enviado a 'Todos los contactos asociados' tras 120 días. Trigger con IDs numéricos crudos. | H177: Alto | I177: Alto | J177: Sin cambio | K177: BNO – Implementación | L177: BNO | N177: Sigue mal (abierto) | O177: No aplica | Q177: Configurar plantilla de correo, limitar destinatario al titular y reemplazar IDs por nombres. | R177: Flow 1808853523 'Congelado Nº03 Notificaciones de reactivación'. Trigger 'Pipeline 890423160 / Etapa 1341314731 / >120 días'. Nodo '1. Enviar correo: Correo desconocido a Todos los contactos asociados'. | T177: Auditoría: Sin cambio | U177: 2026-06-09 00:00:00 | V177: 46191 | W177: Sí
A178: CON-177 | B178: 2ª Auditoría | C178: BIT-060 | D178: Re-validación | E178: 01 Inversionista | F178: WF-040 | G178: Correo de cierre al cliente sin configurar ('Correo desconocido', Se necesitan cambios) a 'Todos los contactos asociados'. Trigger con IDs numéricos crudos. | H178: Alto | I178: Alto | J178: Sin cambio | K178: BNO – Implementación | L178: BNO | N178: Sigue mal (abierto) | O178: No aplica | Q178: Configurar plantilla de correo de cierre, limitar destinatario al titular y reemplazar IDs por nombres. | R178: Flow 1808818002 'Cierre Nº02 Notificaciones a cliente'. Trigger 'Pipeline 890423160 / Etapa 1341314732'. Nodo '1. Enviar correo: Correo desconocido a Todos los contactos asociados'. | T178: Auditoría: Sin cambio | U178: 2026-06-09 00:00:00 | V178: 46191 | W178: Sí
A179: CON-178 | B179: 2ª Auditoría | C179: BIT-062 | D179: Re-validación | E179: 04 ATC | F179: WF-041 | G179: Round-robin configurado como 'distribución aleatorio' (no equitativo). En equipo de 2 puede saturar a uno y dejar libre al otro. | H179: Alto | I179: Alto | J179: Sin cambio | K179: BNO – Implementación | L179: BNO | N179: Sigue mal (abierto) | O179: No aplica | Q179: Cambiar a distribución equitativa/balanceada por carga en el nodo de rotación de propietario. | R179: Flow ID 1822143749. Nodo '1. Rotar registro al propietario': "Rotar ticket entre 1 equipo usando la distribución aleatorio"; detalle confirma rota entre equipo "Atencion al Cliente". WF Activado. | S179: Re-validación; actualiza fila 88 de la 1ª pasada | T179: Auditoría: Sin cambio | U179: 2026-06-09 | V179: 46191 | W179: Sí
A180: CON-179 | B180: 2ª Auditoría | C180: BIT-063 | D180: Re-validación | E180: 04 ATC | F180: WF-041 | G180: Rotación sin lógica de turnos por horario. Si asigna a un agente fuera de turno, el ticket queda sin atender dentro del SLA de 5 min. | H180: Alto | I180: Alto | J180: Sin cambio | K180: BNO – Implementación | L180: BNO | N180: Sigue mal (abierto) | O180: No aplica | Q180: Agregar lógica de disponibilidad/horario laboral antes de asignar, o reglas de turno en la rotación. | R180: Flow ID 1822143749. Nodo 'Rotar registro al propietario' rota entre equipo "Atencion al Cliente" sin condición de horario/disponibilidad. Flujo solo tiene 2 nodos (Rotar + Notificar in-app) y End, sin rama de turnos. | S180: Re-validación; actualiza fila 89 de la 1ª pasada | T180: Auditoría: Sin cambio | U180: 2026-06-09 | V180: 46191 | W180: Sí
A181: CON-180 | B181: 2ª Auditoría | C181: BIT-064 | D181: Re-validación | E181: 04 ATC | F181: WF-042 | G181: Alerta de SLA vencido notifica a 'Raquel Alfie' hardcoded (más Propietario del ticket). Si Raquel cambia de rol queda obsoleto. | H181: Alto | I181: Alto | J181: Sin cambio | K181: BNO – Implementación | L181: BNO | N181: Sigue mal (abierto) | O181: No aplica | Q181: Reemplazar 'Raquel Alfie' por destinatario dinámico por rol/equipo (Dirección Comercial) en vez de usuario hardcoded. | R181: Flow ID 1822144532. Nodo '1. Enviar notificación en la app': "Enviar ALERTA DE SLA: Ticket [Nombre del ticket] sin atencion a Raquel Alfie y Propietario del ticket". WF Activado. | S181: Re-validación; actualiza fila 90 de la 1ª pasada | T181: Auditoría: Sin cambio | U181: 2026-06-09 | V181: 46191 | W181: Sí
A182: CON-181 | B182: 2ª Auditoría | C182: BIT-065 | D182: Re-validación | E182: 04 ATC | F182: WF-043 | G182: Trigger frágil: dispara con 'Ultima actividad es conocido', no con interacción humana del EAC. Pasa ticket a En atencion sin acción real del agente. | H182: Alto | I182: Alto | J182: Sin cambio | K182: BNO – Implementación | L182: BNO | N182: Sigue mal (abierto) | O182: No aplica | Q182: Cambiar trigger a un evento real de respuesta humana del EAC (email/nota enviada por miembro del equipo Atencion al Cliente) en vez de 'Ultima actividad'. | R182: Flow ID 1822143856. Trigger Grupo 1: Estado del ticket = Nuevo Ticket (Servicio al Cliente) Y 'El valor Ultima actividad es conocido' Y 'Propietario del ticket es conocido'. Accion 1 Editar registro: Define Pipeline y estado = En atencion (Servicio al Cliente). WF Activado. | S182: Re-validación; actualiza fila 91 de la 1ª pasada | T182: Auditoría: Sin cambio | U182: 2026-06-09 | V182: 46191 | W182: Sí
A183: CON-182 | B183: 2ª Auditoría | C183: BIT-067 | D183: Re-validación | E183: 04 ATC | F183: WF-044 | G183: WF-043 y WF-044 comparten trigger idéntico y disparan en paralelo; riesgo de desincronización entre cambio de etapa y Fecha primera respuesta. | H183: Alto | I183: Alto | J183: Sin cambio | K183: BNO – Implementación | L183: BNO | N183: Sigue mal (abierto) | O183: No aplica | Q183: Unificar en un solo WF o encadenar secuencialmente: setear Fecha primera respuesta dentro del mismo flujo que mueve a En atencion. | R183: Flow ID 1822145171. Trigger Grupo 1 identico a WF-043 (1822143856): Estado=Nuevo Ticket (Servicio al Cliente) Y 'Ultima actividad es conocido' Y 'Propietario conocido'. Ambos Activados. | S183: Re-validación; actualiza fila 93 de la 1ª pasada | T183: Auditoría: Sin cambio | U183: 2026-06-09 | V183: 46191 | W183: Sí
A184: CON-183 | B184: 2ª Auditoría | C184: BIT-068 | D184: Re-validación | E184: 04 ATC | F184: WF-044 | G184: 'Fecha de primera respuesta' se setea con la fecha de ejecucion del WF, no con la respuesta humana real del EAC. Metrica SLA inflada. | H184: Alto | I184: Alto | J184: Sin cambio | K184: BNO – Implementación | L184: BNO | N184: Sigue mal (abierto) | O184: No aplica | Q184: Setear Fecha primera respuesta a partir del primer email/nota real del EAC, no de la ejecucion del WF. | R184: Flow ID 1822145171. Accion 1 Editar registro: "Define Fecha de primera respuesta como la fecha en que se ejecuto esta accion". Disparada por 'Ultima actividad', no por respuesta del agente. | S184: Re-validación; actualiza fila 94 de la 1ª pasada | T184: Auditoría: Sin cambio | U184: 2026-06-09 | V184: 46191 | W184: Sí
A185: CON-184 | B185: 2ª Auditoría | C185: BIT-071 | D185: Re-validación | E185: 04 ATC | F185: WF-046 | G185: El WF solo cambia etapa a Escalado a TI. No asigna propietario al equipo TI, no notifica a Jesus, no genera folio/registro en TI ni Notion. Ticket queda huerfano. | H185: Alto | I185: Alto | J185: Sin cambio | K185: Compartido BNO+Monific | L185: Compartido (BNO + Monific) | N185: Sigue mal (abierto) | O185: No aplica | Q185: Agregar en el WF: asignar propietario al equipo TI y notificar a Jesus. La generacion de folio/registro en TI/Notion la ejecuta Monific-Tech (Jesus) por cambio de modelo 5-jun. | R185: Flow ID 1822136495. Trigger: Estado=En atencion (Servicio al Cliente) Y Tipo de ticket=Problema tecnico. Unica accion '1. Editar registro': Define Pipeline y estado = Escalado a TI (Servicio al Cliente); luego End. Sin asignacion ni notificacion. | S185: Re-validación; actualiza fila 97 de la 1ª pasada | T185: Auditoría: Sin cambio | U185: 2026-06-09 | V185: 46191 | W185: Sí
A186: CON-185 | B186: 2ª Auditoría | C186: BIT-072 | D186: Re-validación | E186: 04 ATC | F186: WF-047 | G186: Folio TI con formato incorrecto: se arma como 'Tipo de ticket - Fecha de creacion', no como folio estructurado/secuencial unico de TI. | H186: Alto | I186: Alto | J186: Sin cambio | K186: Compartido BNO+Monific | L186: Compartido (BNO + Monific) | N186: Sigue mal (abierto) | O186: No aplica | Q186: Definir folio TI con formato estructurado y unico (ej. prefijo TI + consecutivo + fecha). La generacion la coordina Monific-Tech (Jesus) por cambio de modelo 5-jun. | R186: Flow ID 1822136886. Accion 1 'Editar registro': Define Folio ticket TI como [Tipo de ticket (ticket inscrito)] - [Fecha de creacion (ticket inscrito)]. WF Activado. | S186: Re-validación; actualiza fila 98 de la 1ª pasada | T186: Auditoría: Sin cambio | U186: 2026-06-09 | V186: 46191 | W186: Sí
A187: CON-186 | B187: 2ª Auditoría | C187: BIT-075 | D187: Re-validación | E187: 04 ATC | F187: WF-048 | G187: Correo de ESCALAMIENTO CRITICO va a 'Raquel Alfie' hardcoded. Mismo patron de usuario hardcoded que WF-042. No detectado por separado en 1a pasada. | H187: Alto | I187: Alto | J187: Abierto | K187: BNO – Implementación | L187: BNO | N187: Sigue mal (abierto) | O187: No aplica | Q187: Reemplazar 'Raquel Alfie' por destinatario por rol/equipo (Direccion / TI) en vez de usuario hardcoded. | R187: Flow ID 1822137249. Accion 1 'Enviar notificacion interna por correo': "Enviar ESCALAMIENTO CRITICO: Ticket # [Nombre del ticket] a Raquel Alfie". | T187: Auditoría: Abierto | U187: 2026-06-09 | V187: 46191 | W187: Sí
A188: CON-187 | B188: 2ª Auditoría | C188: BIT-085 | D188: Re-validación | E188: 05 Cobranza | F188: WF-053 | G188: WF-053 'Recordatorios activos': trigger de programacion ANUAL ('Anualmente el 1 de junio'), bug copy-paste. Un recordatorio de cobranza no puede dispararse 1 vez al ano. Sigue DESACTIVADO. | H188: Alto | I188: Alto | J188: Abierto | K188: BNO – Implementación | L188: BNO | N188: Sigue mal (abierto) | O188: No aplica | Q188: Cambiar trigger a programacion recurrente mensual o inscripcion por propiedad de fecha de pago. Reactivar tras correccion. | R188: Flow 1820860306. Trigger: 'En una programacion - Anualmente el 1 de junio entre 10:00 y 17:00 CST'. Condicion: Estado de ticket = Cobranza Activa. Estado: DESACTIVADO. | T188: Auditoría: Abierto | U188: 2026-06-09 00:00:00 | V188: 46191 | W188: Sí
A189: CON-188 | B189: 2ª Auditoría | C189: BIT-086 | D189: Re-validación | E189: 05 Cobranza | F189: WF-053 | G189: WF-053 nodo 'Inscribirse en una secuencia' marcado 'Se necesitan cambios': sequenceId/senderType sin configurar. Inscribe a un CONTACTO en WF de objeto Ticket. | H189: Alto | I189: Alto | J189: Abierto | K189: BNO – Implementación | L189: BNO | N189: Sigue mal (abierto) | O189: No aplica | Q189: Configurar la secuencia real o reemplazar por acciones de email/tarea sobre el ticket. Corregir objeto a Ticket. | R189: Flow 1820860306, nodo 1: literal 'Inscribir al contacto en {{ sequenceId }} de {{ senderType }}' + etiqueta 'Se necesitan cambios'. | T189: Auditoría: Abierto | U189: 2026-06-09 00:00:00 | V189: 46191 | W189: Sí
A190: CON-189 | B190: 2ª Auditoría | C190: BIT-087 | D190: Re-validación | E190: 05 Cobranza | F190: WF-054 | G190: WF-054 'Recordatorios antes del 15 mes': trigger ANUAL ('Anualmente el 11 de junio'), bug copy-paste. Deberia ser mensual antes del dia 15. Sigue DESACTIVADO. | H190: Alto | I190: Alto | J190: Abierto | K190: BNO – Implementación | L190: BNO | N190: Sigue mal (abierto) | O190: No aplica | Q190: Cambiar trigger a programacion mensual previa al dia 15 o inscripcion por propiedad de fecha. Reactivar tras correccion. | R190: Flow 1820860318. Trigger: 'Anualmente el 11 de junio entre 10:00 y 17:00 CST'. Acciones: 1) Retraso L-V; 2) Inscribirse en secuencia (rota). DESACTIVADO. | T190: Auditoría: Abierto | U190: 2026-06-09 00:00:00 | V190: 46191 | W190: Sí
A191: CON-190 | B191: 2ª Auditoría | C191: BIT-088 | D191: Re-validación | E191: 05 Cobranza | F191: WF-054 | G191: WF-054 nodo 'Inscribirse en una secuencia' marcado 'Se necesitan cambios': sequenceId/senderType sin configurar. Mismo bug que WF-053. | H191: Alto | I191: Alto | J191: Abierto | K191: BNO – Implementación | L191: BNO | N191: Sigue mal (abierto) | O191: No aplica | Q191: Configurar la secuencia real o reemplazar por email/tarea sobre el ticket. Corregir objeto a Ticket. | R191: Flow 1820860318, nodo 2: literal 'Inscribir al contacto en {{ sequenceId }} de {{ senderType }}' + etiqueta 'Se necesitan cambios'. | T191: Auditoría: Abierto | U191: 2026-06-09 00:00:00 | V191: 46191 | W191: Sí
A192: CON-191 | B192: 2ª Auditoría | C192: BIT-090 | D192: Nuevo ARI | E192: 05 Cobranza | F192: WF-055 | G192: WF-055 escalamiento Dia 16 (Mora Temprana) no incluye al despacho externo (ARI), que segun acuerdo participa en paralelo en cobranza amistosa desde el Dia 16. | H192: Alto | I192: Alto | J192: Abierto | K192: Despacho externo (ARI) | L192: Despacho externo (ARI) | N192: Sigue mal (abierto) | O192: No aplica | Q192: Agregar al futuro equipo 'Despacho externo' como destinatario en el escalamiento Dia 16 para activar cobranza amistosa en paralelo. | R192: Flow 1820890946. Retraso 15 dias + accion 4 'ESCALAMIENTO 16 Dias' solo a Raquel y Vianey. No hay accion que notifique al despacho (ARI). | T192: Auditoría: Abierto | U192: 2026-06-09 00:00:00 | V192: 46191 | W192: No
A193: CON-192 | B193: 2ª Auditoría | C193: BIT-091 | D193: Otro | E193: 05 Cobranza | F193: WF-055 | G193: WF-055 incoherencia: trigger exige 'fecha de pago hace mas de 31 dias' pero el contenido habla de 'Mora Dia 1' y escala a 'Dia 16'. La condicion de 31 dias retrasa todo el ciclo de recordatorios. | H193: Alto | I193: Alto | J193: Abierto | K193: BNO – Implementación | L193: BNO | N193: Sigue mal (abierto) | O193: No aplica | Q193: Revisar la ventana del trigger: alinear con Dia 1 post-vencimiento si ese es el objetivo, o corregir los textos de las acciones. | R193: Flow 1820890946 trigger: 'Estado de ticket = Cobranza Activa Y Estado de pago = Atrasado Y fecha de pago es mas que Hace mas de 31 dias'. Contenido refiere Dia 1 y Dia 16. | T193: Auditoría: Abierto | U193: 2026-06-09 00:00:00 | V193: 46191 | W193: Sí
A194: CON-193 | B194: 2ª Auditoría | C194: BIT-095 | D194: Otro | E194: 05 Cobranza | F194: WF-058 | G194: WF-058 notif 'Cambio de Etapa: Decision de Refinanciamiento' no tiene destinatarios configurados (campo 'a y .' vacio). El aviso no llega a nadie. | H194: Alto | I194: Alto | J194: Abierto | K194: BNO – Implementación | L194: BNO | N194: Sigue mal (abierto) | O194: No aplica | Q194: Configurar destinatarios (equipo Cobranza / comite de refinanciamiento) en la notificacion. | R194: Flow 1820913996, accion 2 'Enviar notificacion interna por correo': 'Cambio de Etapa: Decision de Refinanciamiento | Nombre del ticket' a (vacio). | T194: Auditoría: Abierto | U194: 2026-06-09 00:00:00 | V194: 46191 | W194: Sí
A195: CON-194 | B195: 2ª Auditoría | C195: BIT-096 | D195: Nuevo ARI | E195: 05 Cobranza | F195: WF-058 | G195: WF-058 tarea 'Validacion Juridica: Refinanciamiento' (accion 4) queda SIN asignatario (campo 'a .' vacio). Ademas deberia asignarse al despacho externo (ARI). | H195: Alto | I195: Alto | J195: Abierto | K195: Despacho externo (ARI) | L195: Despacho externo (ARI) | N195: Sigue mal (abierto) | O195: No aplica | Q195: Asignar la tarea de validacion juridica al despacho externo (ARI) como responsable de refinanciamiento. | R195: Flow 1820913996, accion 4 'Crear tarea': 'Validacion Juridica: Refinanciamiento de Cobranza | Nombre del ticket' y asignarla a (vacio). | T195: Auditoría: Abierto | U195: 2026-06-09 00:00:00 | V195: 46191 | W195: No
A196: CON-195 | B196: 2ª Auditoría | C196: BIT-007 | D196: Equipos | E196: Transversal | F196: Transversal | G196: Existen equipos "Asesor de atención a solicitantes" y "Asesor de atención a inversionistas" como equipo predeterminado de usuarios, pero no figuran en la lista oficial de equipos. | H196: Medio | I196: Medio | J196: Abierto | K196: Compartido BNO+Monific | L196: Compartido (BNO + Monific) | N196: Sigue mal (abierto) | O196: No aplica | Q196: Normalizar nomenclatura: registrar estos equipos formalmente o reasignar a un equipo oficial; afecta trazabilidad de quién recibe notificaciones. | R196: Users: Guillermo Gomez → "Asesor de atención a solicitantes"; Raquel Alfie → "Asesor de atención a inversionistas". Lista de equipos solo muestra 9, sin estos nombres. | T196: Auditoría: Abierto | U196: 2026-06-08 00:00:00 | V196: 46191 | W196: Sí
A197: CON-196 | B197: 2ª Auditoría | C197: BIT-008 | D197: Equipos | E197: Transversal | F197: Transversal | G197: Jesús Torres (ejecutor técnico principal del modelo BNO-capacita/TI-ejecuta) no tiene equipo predeterminado asignado. | H197: Medio | I197: Medio | J197: Abierto | K197: Monific – Tech (Jesús) | L197: Monific – TI | N197: Sigue mal (abierto) | O197: No aplica | Q197: Asignar a Jesús a un equipo (TI/Tech) para que reciba asignaciones/escalamientos previstos en el nuevo modelo operativo. | R197: Users: jesus.torres@monific.com, Superadministrador, "Equipo predeterminado" = "--". | T197: Auditoría: Abierto | U197: 2026-06-08 00:00:00 | V197: 46191 | W197: No
A198: CON-197 | B198: 2ª Auditoría | C198: BIT-010 | D198: Nuevo cambio modelo BNO-TI | E198: 05 Cobranza | F198: WF Cobranza Etapa 02 Nº03 (Recordatorios y tareas venc.15) | G198: WF marcado "Activado" pero sin acciones configuradas (0 nodos de acción); no genera recordatorios ni tareas. | H198: Medio | I198: Medio | J198: Abierto | K198: BNO – Implementación | L198: BNO | N198: Sigue mal (abierto) | O198: No aplica | Q198: Completar las acciones de recordatorio/tarea o desactivar el WF para evitar falsa sensación de cobertura. | R198: Canvas flow 1820890946: solo trigger ("Estado=Cobranza Activa, pago Atrasado >31 días") + botón "Agregar nueva acción"; 0 inscritos. | T198: Auditoría: Abierto | U198: 2026-06-08 00:00:00 | V198: 46191 | W198: Sí
A199: CON-198 | B199: 2ª Auditoría | C199: BIT-029 | D199: Re-validación | E199: 02 Solicitante | F199: WF-018 | G199: WF-018 ahora EXIGE 'Contrato firmado=Sí' en el trigger. La race condition reportada antes (WF-018 ganaba a WF-022 sin exigir firma) parece mitigada. Re-evaluar BITs de WF-022/023. | H199: Medio | I199: Medio | J199: En curso | K199: Monific – Tech (Jesús) | L199: Monific – TI | N199: En curso (BNO) | O199: No aplica | Q199: Validar en sandbox que WF-022 (a perdido) y WF-018 (a ganado) ya no compiten. Confirmar mutuamente excluyentes. | R199: Flow 1808711272 'Etapa 04 Nº01 Cambio de etapa a ganado'. Trigger: Proceso de firma + 'Contrato firmado es cualquiera de Sí', Reinscripción desactivada. Acción 1 edita etapa a Ganado. | T199: Auditoría/BNO: en curso, sin entregar | U199: 2026-06-09 00:00:00 | V199: 46191 | W199: No
A200: CON-199 | B200: 2ª Auditoría | C200: BIT-034 | D200: Re-validación | E200: 02 Solicitante | F200: WF-022 | G200: Race condition con WF-018 RESUELTA: WF-018 exige Contrato firmado=Sí y WF-022 exige Contrato firmado=No. Ahora son mutuamente excluyentes. Confirmar en sandbox. | H200: Medio | I200: Medio | J200: Resuelto | K200: Monific – Tech (Jesús) | L200: Monific – TI | N200: Validado (resuelto) | O200: No aplica | Q200: Validar en sandbox que ya no hay doble disparo. Cerrar el hallazgo de race si pasa la prueba. | R200: Flow 1808890501 'Etapa 04 Nº05 Enviar a perdido'. Trigger: Proceso de firma + 'Contrato firmado es cualquiera de No'. WF-018 exige 'Contrato firmado=Sí'. | S200: Re-validación; actualiza fila 53.0 de la 1ª pasada | T200: Auditoría: Resuelto y aplicado | U200: 2026-06-09 00:00:00 | V200: 46191 | W200: No
A201: CON-200 | B201: 2ª Auditoría | C201: BIT-036 | D201: Re-validación | E201: 02 Solicitante | F201: WF-023 | G201: Fecha de cierre se fija como la fecha de ejecución del WF, no la fecha real de firma del contrato. Puede quedar desfasada. La race con WF-024 ya no aplica (etapas distintas). | H201: Medio | I201: Medio | J201: Sin cambio | K201: BNO – Implementación | L201: BNO | N201: Sigue mal (abierto) | O201: No aplica | Q201: Usar la fecha real de firma del contrato (propiedad) en lugar de la fecha de ejecución del WF. | R201: Flow 1808853378 'Etapa 05 Nº01 Establecer fecha de cierre'. Trigger: etapa=Ganado. Acción 1: 'Define Fecha de cierre como la fecha en que se ejecutó esta acción'. | S201: Re-validación; actualiza fila 55.0 de la 1ª pasada | T201: Auditoría: Sin cambio | U201: 2026-06-09 00:00:00 | V201: 46191 | W201: Sí
A202: CON-201 | B202: 2ª Auditoría | C202: BIT-040 | D202: Re-validación | E202: 01 Inversionista | F202: WF-025 a WF-040 | G202: WF-025 (Cambio a Activo) no escribe propiedades de trazabilidad CNBV (fecha/usuario/motivo) en el cambio de etapa. | H202: Medio | I202: Medio | J202: Sin cambio | K202: BNO – Implementación | L202: BNO | N202: Sigue mal (abierto) | O202: No aplica | Q202: Agregar set de propiedades de trazabilidad (fecha de cambio, usuario, motivo) al cambio de etapa. | R202: Flow 1808818247 'Perfil Nº01 Cambio de etapa a activo'. Única acción '1. Editar registro: define etapa como Inversionista Activo'. Desactivado. | T202: Auditoría: Sin cambio | U202: 2026-06-09 00:00:00 | V202: 46191 | W202: Sí
...

Sheet Comunicaciones (81)
A1: ID | B1: Área | C1: Comunicación | D1: Canal | E1: Trigger | F1: Destinatario | G1: Responsable | H1: Responsable BNO | I1: Propiedad | J1: Tokens | K1: Estado objetivo | L1: Estado de implementación | M1: % avance | N1: Fecha objetivo | O1: Validación Monific (Raquel) | P1: Link al asset HubSpot | Q1: Notas / Bloqueos
A2: SOL-001 | B2: Solicitantes | C2: Confirmación de solicitud recibida | D2: Email | E2: Formulario / negocio nuevo | F2: Solicitante | G2: A.A.S. | I2: PB-SOL-NEW | J2: TK-BASE + TK-SOL | K2: Crear | L2: No iniciado | M2: 0.0 | O2: Pendiente
A3: SOL-002 | B3: Solicitantes | C3: Solicitud de documentación inicial | D3: Email | E3: Califica pre-revisión | F3: Solicitante | G3: A.A.S. | I3: PB-SOL-NEW | J3: TK-BASE + TK-SOL | K3: Crear | L3: No iniciado | M3: 0.0 | O3: Pendiente
A4: SOL-003 | B4: Solicitantes | C4: Recordatorio documentación día 3 | D4: Email | E4: 3 días sin carga completa | F4: Solicitante | G4: A.A.S. | I4: PB-SOL-NEW | J4: TK-BASE + TK-SOL | K4: Crear | L4: No iniciado | M4: 0.0 | O4: Pendiente
A5: SOL-004 | B5: Solicitantes | C5: Recordatorio documentación día 6 | D5: Email | E5: 6 días sin carga completa | F5: Solicitante | G5: A.A.S. | I5: PB-SOL-NEW | J5: TK-BASE + TK-SOL | K5: Crear | L5: No iniciado | M5: 0.0 | O5: Pendiente
A6: SOL-005 | B6: Solicitantes | C6: No show o sin respuesta | D6: Email | E6: Cita vencida o 7 días sin respuesta | F6: Solicitante | G6: A.A.S. | I6: PB-SOL-NEW | J6: TK-BASE + TK-SOL | K6: Crear | L6: No iniciado | M6: 0.0 | O6: Pendiente
A7: SOL-006 | B7: Solicitantes | C7: Dudas sobre requisitos | D7: Email | E7: Solicitante pide orientación | F7: Solicitante | G7: A.A.S. | I7: PB-SOL-NEW | J7: TK-BASE + TK-SOL | K7: Crear | L7: No iniciado | M7: 0.0 | O7: Pendiente
A8: SOL-007 | B8: Solicitantes | C8: Pausa voluntaria | D8: Email | E8: Solicitante decide pausar | F8: Solicitante | G8: A.A.S. | I8: PB-SOL-NEW | J8: TK-BASE + TK-SOL | K8: Crear | L8: No iniciado | M8: 0.0 | O8: Pendiente
A9: SOL-008 | B9: Solicitantes | C9: Carpeta Drive creada | D9: WhatsApp | E9: Carpeta de expediente creada | F9: Solicitante | G9: A.A.S. | I9: PB-SOL-NEW | J9: TK-BASE + TK-SOL | K9: Crear | L9: No iniciado | M9: 0.0 | O9: Pendiente
A10: SOL-009 | B10: Solicitantes | C10: Expediente completo | D10: Email | E10: Validación documental completa | F10: Solicitante | G10: A.A.S. | I10: PB-SOL-NEW | J10: TK-BASE + TK-SOL | K10: Crear | L10: No iniciado | M10: 0.0 | O10: Pendiente
A11: SOL-010 | B11: Solicitantes | C11: Expediente con observaciones | D11: Email | E11: Validación documental parcial | F11: Solicitante | G11: A.A.S. | I11: PB-SOL-NEW | J11: TK-BASE + TK-SOL | K11: Crear | L11: No iniciado | M11: 0.0 | O11: Pendiente
A12: SOL-011 | B12: Solicitantes | C12: No viable documental | D12: Email | E12: Documentación no subsanable | F12: Solicitante | G12: A.A.S. | I12: PB-SOL-NEW | J12: TK-BASE + TK-SOL | K12: Crear | L12: No iniciado | M12: 0.0 | O12: Pendiente
A13: SOL-012 | B13: Solicitantes | C13: Avance a evaluación financiera | D13: Email | E13: Pasa a análisis financiero | F13: Solicitante | G13: A.A.S. | I13: PB-SOL-NEW | J13: TK-BASE + TK-SOL | K13: Crear | L13: No iniciado | M13: 0.0 | O13: Pendiente
... A82: PDF-004 | B82: PDF institucional | C82: Carta de refinanciamiento | D82: PDF | E82: Reestructura aprobada | F82: Solicitante | G82: Legal / Owner de pipeline | I82: PB-COB-REFI | J82: TK-BASE + TK-COB + TK-PDF | K82: Crear | L82: No iniciado | M82: 0.0 | O82: Pendiente
B84: NOTA: el TEXTO/COPY de cada comunicación (asunto + cuerpo + tokens) está en el documento «Matriz completa de comunicación» — Parte II (Biblioteca de plantillas y textos). Esta hoja lleva el control de implementación; el contenido para pegar vive en ese anexo.

Sheet WF estado real (96)
A1: # | B1: Workflow (nombre real en HubSpot) | C1: Estado | D1: Validación Monific (Raquel) | E1: Creado | F1: Últ. modificación
A2: 1 | B2: WF | Form: Inversionista | C2: OFF | D2: Sigue mal (apagado) | E2: 2025-03-14 | F2: 2025-07-02
A3: 2 | B3: WF | Notificaciones de cobro | C3: OFF | D3: Sigue mal (apagado) | E3: 2025-03-24 | F3: 2025-04-28
A4: 3 | B4: El pipeline es "Solicitud de financiamiento", la etapa es "Publicación" | C4: OFF | D4: Sigue mal (apagado) | E4: 2025-04-07 | F4: 2025-07-25
A5: 4 | B5: Seguimiento de encuesta personalizada 4 - Detractor | C5: OFF | D5: Sigue mal (apagado) | E5: 2025-04-21 | F5: 2025-04-21
A6: 5 | B6: El pipeline es "inversión", la etapa es "Depósito" | C6: OFF | D6: Sigue mal (apagado) | E6: 2025-04-28 | F6: 2025-04-28
A7: 6 | B7: Asignación de propietario | Contactos sin | C7: OFF | D7: Sigue mal (apagado) | E7: 2025-05-21 | F7: 2025-08-12
A8: 7 | B8: Campañas Meta | Asignación | C8: OFF | D8: Sigue mal (apagado) | E8: 2025-06-03 | F8: 2025-06-03
A9: 8 | B9: Creación de lead | Inversionistas | C9: OFF | D9: Sigue mal (apagado) | E9: 2025-06-18 | F9: 2025-06-18
A10: 9 | B10: El pipeline es "Inversionistas", la etapa es "Inversión activa" | C10: OFF | D10: Sigue mal (apagado) | E10: 2025-06-18 | F10: 2025-06-18
A11: 10 | B11: WF | Notificaciones de cobro ACTUALIZADO | C11: OFF | D11: Sigue mal (apagado) | E11: 2025-06-18 | F11: 2025-07-22
A12: 11 | B12: Recordatorio pago de préstamo general | SOLICITUDES | C12: OFF | D12: Sigue mal (apagado) | E12: 2025-06-25 | F12: 2025-06-25
A13: 12 | B13: MODELO Notificaciones de cobro | Tickets | C13: OFF | D13: Sigue mal (apagado) | E13: 2025-06-30 | F13: 2025-07-03
... A97: 96 | B97: 01. Contactos | 01. Datos | Nº 01 | Crear negocio de solicitante o inversionistas | V1 | C97: ON | D97: Validado (activo) | E97: 2026-06-05 | F97: 2026-06-08
B99: Nota: «Validado (activo)» = el workflow está ENCENDIDO al 17-jun-2026; NO certifica que la lógica interna (nodos, correos, tokens) sea correcta — eso se valida abriendo el flow. «Sigue mal (apagado)» = desactivado. Ajusta cada fila con el menú si revisas la lógica.

Sheet WF lógica (detalle API)
A1: # | B1: Workflow | C1: Estado | D1: Nodos | E1: ¿Envía correo? | F1: Solo set_property (no comunica) | G1: ¿Secuencia? | H1: Token texto plano | I1: ¿Notifica a BNO (Ochoa)?
A2: 1 | B2: 01. Contactos | 01. Datos | Nº 01 | Crear negocio de solicitante o inversionistas | V1 | C2: True | D2: 60 | E2: No | F2: Sí | G2: No | H2: Sí | I2: No
A3: 2 | B3: 03. Negocios | 01. Solicitantes | Etapa 01: Nuevo | Nº 01 | Cambio de etapa a Evaluación | V1 | C3: True | D3: 3 | E3: No | F3: Sí | G3: No | H3: No | I3: No
A4: 3 | B4: 03. Negocios | 01. Solicitantes | Etapa 01: Nuevo | Nº 02 | Tarea de creación de drive | V1 | C4: True | D4: 21 | E4: No | F4: Sí | G4: No | H4: Sí | I4: No
A5: 4 | B5: 03. Negocios | 01. Solicitantes | Etapa 01: Nuevo | Nº 03 | Actualizar estatus y enviar secuencia | V1 | C5: True | D5: 20 | E5: No | F5: Sí | G5: Sí | H5: Sí | I5: No
A6: 5 | B6: 03. Negocios | 01. Solicitantes | Etapa 01: Nuevo | Nº 04 | Enviar secuencia desde contacto + 15 días | V1 | C6: False | D6: 17 | E6: No | F6: Sí | G6: Sí | H6: Sí | I6: No
A7: 6 | B7: 03. Negocios | 01. Solicitantes | Etapa 01: Nuevo | Nº 05 | Enviar a solicitante requerimiento de su documentación | V1 | C7: True | D7: 4 | E7: No | F7: Sí | G7: No | H7: No | I7: No
A8: 7 | B8: 03. Negocios | 01. Solicitantes | Etapa 01: Nuevo | Nº 07 | Enviar secuencia desde contacto + 2 días | V1 | C8: False | D8: 17 | E8: No | F8: Sí | G8: Sí | H8: Sí | I8: No
A9: 8 | B9: 03. Negocios | 01. Solicitantes | Etapa 01: Nuevo | Nº 08 | Enviar secuencia Post formulario | V1 | C9: False | D9: 13 | E9: No | F9: Sí | G9: Sí | H9: Sí | I9: No
A10: 9 | B10: 03. Negocios | 01. Solicitantes | Etapa 02: Evaluación | Nº 01 | Cambio de etapa a Formalización | V1 | C10: True | D10: 3 | E10: No | F10: Sí | G10: No | H10: No | I10: No
A11: 10 | B11: 03. Negocios | 01. Solicitantes | Etapa 02: Evaluación | Nº 02 | Cambio de etapa a perdido | V1 | C11: True | D11: 3 | E11: No | F11: Sí | G11: No | H11: No | I11: No
A12: 11 | B12: 03. Negocios | 01. Solicitantes | Etapa 02: Evaluación | Nº 05 | fijar la propiedad "Fecha de decisión del comité" | V1 | C12: True | D12: 3 | E12: No | F12: Sí | G12: No | H12: No | I12: No
A13: 12 | B13: 03. Negocios | 01. Solicitantes | Etapa 02: Evaluación | Nº 06 | Crear tarea de la carta de aceptación | V1 | C13: True | D13: 9 | E13: No | F13: Sí | G13: No | H13: Sí | I13: No
... A97: 96 | B97: WF | Form: Solicitud de financiamiento | C97: True | D97: 110 | E97: Sí | F97: No | G97: No | H97: Sí | I97: No
B99: Resumen: de 96 workflows, 9 envían correo y 85 solo hacen set_property sin comunicar. 26 nodos inscriben a secuencia SIN sequenceId. 701 nodos con token en texto plano. 21 nodos de notificación interna, 3 a David Ochoa (BNO).
B101: Nodos de notificación interna a David Ochoa (BNO) — actionTypeId 0-8:
B102: • 03. Negocios | 01. Solicitantes | Etapa 02: Evaluación | Nº 04 | Correo interno a DG | V1 | C102: → asunto: | D102: Nuevo solicitante enviado a evaluación
B103: • 03. Negocios | 01. Solicitantes | Etapa 03: Formalización | Nº 03 | Notificación interna a superior estancado | V1 | C103: → asunto: | D103: Escalamiento por apoyo en formalización
B104: • 03. Negocios | 01. Solicitantes | Etapa 04: Proceso de firma | Nº 01 | Cambio de etapa a ganado | V1 | C104: → asunto: | D104: Solicitud de publicación de campaña en Monific

Sheet Verificación 31 propiedades
A1: # | B1: ID | C1: Área | D1: Etiqueta | E1: Nombre interno sugerido | F1: Objeto | G1: Prioridad | H1: Resultado (API 17-jun) | I1: Detalle
A2: 1 | B2: NEW-PROP-001 | C2: Comercial | D2: Tipo de cliente | E2: tipo_de_cliente | F2: Deal | G2: P1 | H2: EXISTE | I2: creada 2025-03-17 (userId 11260213)
A3: 2 | B3: NEW-PROP-002 | C3: Comercial | D3: Canal de entrada | E3: canal_de_entrada | F3: Contact | G3: P1 | H3: EXISTE (por etiqueta) | I3: coincide por etiqueta, nombre interno distinto
A4: 3 | B4: NEW-PROP-003 | C4: Comercial | D4: Fuente de Lead | E4: fuente_de_lead | F4: Contact | G4: P1 | H4: EXISTE (por etiqueta) | I4: coincide por etiqueta, nombre interno distinto
A5: 4 | B5: NEW-PROP-004 | C5: Comercial | D5: Nombre de Broker | E5: nombre_de_broker | F5: Contact | G5: P2 | H5: EXISTE (por etiqueta) | I5: coincide por etiqueta, nombre interno distinto
A6: 5 | B6: NEW-PROP-005 | C6: Servicio | D6: Fecha y hora de atención del ticket | E6: fecha_y_hora_de_atencion_del_ticket | F6: Ticket | G6: P1 | H6: NO EXISTE | I6: no encontrada por nombre ni etiqueta al 17-jun-2026
A7: 6 | B7: NEW-PROP-006 | C7: Cobranza | D7: ID Campaña | E7: id_campana | F7: Custom Object (Cobranza) — confirmar con BNO | G7: P1 | H7: NO EXISTE | I7: no encontrada por nombre ni etiqueta al 17-jun-2026
A8: 7 | B8: NEW-PROP-007 | C8: Cobranza | D8: Propietario de campaña | E8: propietario_de_campana | F8: Custom Object (Cobranza) — confirmar con BNO | G8: P1 | H8: NO EXISTE | I8: no encontrada por nombre ni etiqueta al 17-jun-2026
A9: 8 | B9: NEW-PROP-008 | C9: Cobranza | D9: Link de expediente en Drive | E9: link_de_expediente_en_drive | F9: Custom Object (Cobranza) — confirmar con BNO | G9: P2 | H9: NO EXISTE | I9: no encontrada por nombre ni etiqueta al 17-jun-2026
A10: 9 | B10: NEW-PROP-009 | C10: Cobranza | D10: Condiciones especiales del proyecto | E10: condiciones_especiales_del_proyecto | F10: Custom Object (Cobranza) — confirmar con BNO | G10: P2 | H10: NO EXISTE | I10: no encontrada por nombre ni etiqueta al 17-jun-2026
A11: 10 | B11: NEW-PROP-010 | C11: Cobranza | D11: Nota de acuerdo de pago | E11: nota_de_acuerdo_de_pago | F11: Custom Object (Cobranza) — confirmar con BNO | G11: P1 | H11: NO EXISTE | I11: no encontrada por nombre ni etiqueta al 17-jun-2026
A12: 11 | B12: NEW-PROP-011 | C12: Cobranza | D12: Número de intentos de contacto | E12: numero_de_intentos_de_contacto | F12: Custom Object (Cobranza) — confirmar con BNO | G12: P2 | H12: NO EXISTE | I12: no encontrada por nombre ni etiqueta al 17-jun-2026
... A32: 31 | B32: NEW-PROP-031 | C32: Cobranza | D32: Observaciones del proceso legal | E32: observaciones_del_proceso_legal | F32: Custom Object (Cobranza) — confirmar con BNO | G32: P2 | H32: NO EXISTE | I32: no encontrada por nombre ni etiqueta al 17-jun-2026

Sheet Auditoría API 17-jun
B1: Auditoría técnica por API privada — estado real de HubSpot
B2: Extracción de SOLO LECTURA (no modifica HubSpot) · 17-jun-2026 10:06
B4: Metadata de la extracción
B5: Hub ID | C5: 48427391
B6: App ID (extractor) | C6: 42961396
B7: Scopes | C7: 33
B8: Endpoints exitosos / con error | C8: 28 / 5
B9: Workflows detectados | C9: 96
B10: Propiedades detectadas | C10: 2142
B12: Hechos verificados (evidencia objetiva)
B13: Workflows APAGADOS (de 96) | C13: 39 ← ON: 57
B14: Propiedades de las 31 de BNO que NO existen | C14: 26 de 31 (existen: 5)
B15: · por nombre interno exacto, existen solo | C15: 2 de 31
B17: Cómo se usa esto
B18: Es la 'verdad de campo' fechada que respalda los hallazgos: ver pestañas «WF estado real (96)» y «Verificación 31 propiedades». El archivo crudo completo (2,142 propiedades, JSON por endpoint) es el Excel maestro de la extracción, que se conserva como anexo de evidencia.
B20: Hallazgos adicionales verificados (2ª pasada, 17-jun)
B21: Custom objects en el portal | C21: 0 → el objeto de Cobranza NO existe
B22: Usuarios con acceso al portal | C22: 17 (6 BNO + 2 externos + Monific)
B23: · Usuarios de Black & Orange (proveedor) aún activos | C23: 6
B24: · Abogados externos (fulmentfi.com) con acceso de usuario y owner | C24: 2
B25: Pipelines de negocios | C25: 5 — sin «Mercado Secundario» ni «UNE»
B26: Equipos (teams) | C26: 15 — sin equipo dedicado para ARI
B28: Limitaciones de la extracción
B29: Secuencias (sequences): no se pudieron extraer (error de API) → los hallazgos de secuencias de cobranza NO quedan verificados por API.
B30: «posibles_duplicados» (1,725): casi todos son propiedades NATIVAS de HubSpot con nombres parecidos; no es evidencia sólida salvo casos puntuales.
B31: 60 marketing emails existen, pero NO equivalen a las 81 comunicaciones transaccionales del alcance.
B33: Reconciliación de propiedades (Matriz de masters vs estado real)
B34: Propiedades esperadas por los masters | C34: 177
B35: Encontradas en HubSpot (por etiqueta exacta) | C35: 128
B36: No encontradas en HubSpot | C36: 31 (candidatas a crear)
B37: De las existentes 'accionables', con 0% de llenado | C37: 35 (creadas pero vacías)
B39: Atribución: quién creó la configuración (propiedades 2025-2026)
B40: Creadas por Black & Orange (proveedor) | C40: 135 (Ochoa 76 · Bersot 59)
B41: Creadas por Monific | C41: 20
B42: Sin atribución a usuario actual (legacy/sistema/desactivados) | C42: 643
B43: Formularios en el portal | C43: 3
B45: Limitación clave de esta extracción
B46: El extractor obtuvo la LISTA de workflows (estado ON/OFF), NO el detalle interno de cada flow (nodos, destinatarios, tokens, sequenceId). Por eso los hallazgos de lógica interna (notifica a Ochoa/Bersot, set_property sin correo, secuencia sin sequenceId, UNE sin folio) se sostienen en las auditorías manuales, no en esta API.
B48: Lógica de workflows — VERIFICADA por API (17-jun 11:02, 4,848 nodos)
B49: Workflows que envían correo al cliente | C49: 9 de 96
B50: Workflows que SOLO hacen set_property (no comunican) | C50: 85 de 96
B51: Nodos que inscriben a secuencia SIN sequenceId (rotos) | C51: 26
B52: Nodos con token en texto plano | C52: 701 (en 45 workflows)
B53: Nodos de notificación interna a David Ochoa (BNO) | C53: 3
B54: → asuntos: Nuevo solicitante enviado a evaluación · Escalamiento por apoyo en formalización · Solicitud de publicación de campaña en Monific
B55: Nota: la 'limitación' anterior (no se veía la lógica) YA NO APLICA: se extrajo el detalle nodo por nodo. Solo las secuencias como objeto siguen sin extraerse.

Sheet Acceso y config (API)
B1: Acceso y configuración — estado real (API 17-jun-2026)
B3: Usuarios con acceso al portal (17)
B4: Email | C4: Nombre | D4: Dominio | E4: Clasificación
B5: leticia@black-n-orange.com | C5: Letícia Gonçalves | D5: black-n-orange.com | E5: BNO (proveedor)
B6: jorge@black-n-orange.com | C6: Desarrollador Black and Orange | D6: black-n-orange.com | E6: BNO (proveedor)
B7: jcordova@black-n-orange.com | C7: Jazmin Cordova | D7: black-n-orange.com | E7: BNO (proveedor)
B8: dochoa@black-n-orange.com | C8: David Ochoa | D8: black-n-orange.com | E8: BNO (proveedor)
B9: vgustin@black-n-orange.com | C9: Vanessa Gustin | D9: black-n-orange.com | E9: BNO (proveedor)
B10: analuisa@monific.com | C10: Ana Luisa Becerril Martínez | D10: monific.com | E10: Monific
B11: raquel@monific.com | C11: Raquel Alfie | D11: monific.com | E11: Monific
B12: jesus.torres@monific.com | C12: JESUS TORRES | D12: monific.com | E12: Monific
B13: ted@monific.com | C13: Ted Senado Sacal | D13: monific.com | E13: Monific
B14: emiliano@monific.com | C14: Miguel Emiliano Chacon Lopez | D14: monific.com | E14: Monific
B15: vianey@monific.com | C15: Vianey Correa | D15: monific.com | E15: Monific
... B21: emontes@fulmentfi.com | C21: Evelyn Montes | D21: fulmentfi.com | E21: Externo — Abogados (despacho)
B23: Owners por dominio
B24: Dominio | C24: Owners
B25: monific.com | C25: 9
B26: black-n-orange.com | C26: 6
B27: fulmentfi.com | C27: 2
B28: aichatbot.na1.hubspot.com | C28: 1
B30: Equipos / teams (15)
B31: Ventas · Asesor de atención a solicitantes · Finanzas · Legal · PLD · Asesor de atención a inversionistas · Black and Orange · Evaluación técnica · Inversionistas · Atención al Cliente · Comite de aprobacíón · Marketing · Solicitantes · Evaluación jurídica · Evaluación financiera
B33: Pipelines de negocios (5)
B34: Solicitud de financiamiento
B35: inversión
B36: Proceso de cobranzas
B37: Pipeline Solicitantes
B38: Pipeline Inversionistas
B40: Configuración (resumen)
B41: Custom objects | C41: 0 (el objeto de Cobranza no existe)
B42: Marketing emails | C42: 60
B43: Mercado Secundario / UNE como pipeline | C43: No existen
B45: Atribución de configuración (propiedades 2025-2026)
B46: Creador | C46: Propiedades
B47: Black & Orange (proveedor) | C47: 135
B48: Monific | C48: 20
B49: Legacy / sistema / desactivados | C49: 643
B51: Nota sobre abogados externos (fulmentfi.com)
B52: Francisco Rodríguez (dirección) y Evelyn Montes, del despacho de abogados externos, tienen acceso como USUARIO y como OWNER al portal. No hay equipo segregado; conviven con datos de todos los pipelines. Revisar contra Ley Fintech y el compromiso de BNO de crear equipo dedicado (B14).

Sheet Resumen
B1: MONIFIC × BNO — Resumen de hallazgos
B3: Total de registros | C3: =COUNTA('Hallazgos consolidados'!$A$2:$A$5000) -> 284
B5: Por origen
B6: Categoría | C6: Registros
B7: 1ª Auditoría (+ dictamen BNO) | C7: =COUNTIF('Hallazgos consolidados'!$B$2:$B$5000,"1ª Auditoría (+ dictamen BNO)") -> 112
B8: 2ª Auditoría | C8: =COUNTIF('Hallazgos consolidados'!$B$2:$B$5000,"2ª Auditoría") -> 109
B9: 3ª Bitácora técnica | C9: =COUNTIF('Hallazgos consolidados'!$B$2:$B$5000,"3ª Bitácora técnica") -> 57
B10: 4ª Auditoría Comunicaciones | C10: =COUNTIF('Hallazgos consolidados'!$B$2:$B$5000,"4ª Auditoría Comunicaciones") -> 6
B12: Por prioridad (norm.) — hallazgos de auditoría
B13: Categoría | C13: Registros
B14: Crítico | C14: =COUNTIF('Hallazgos consolidados'!$I$2:$I$5000,"Crítico") -> 103
B15: Alto | C15: =COUNTIF('Hallazgos consolidados'!$I$2:$I$5000,"Alto") -> 101
B16: Medio | C16: =COUNTIF('Hallazgos consolidados'!$I$2:$I$5000,"Medio") -> 58
B17: Bajo | C17: =COUNTIF('Hallazgos consolidados'!$I$2:$I$5000,"Bajo") -> 22
B18: Informativo | C18: =COUNTIF('Hallazgos consolidados'!$I$2:$I$5000,"Informativo") -> 0
B20: Quién debe actuar (norm.)
B21: Categoría | C21: Registros
B22: BNO | C22: =COUNTIF('Hallazgos consolidados'!$L$2:$L$5000,"BNO") -> 182
B23: Compartido (BNO + Monific) | C23: =COUNTIF('Hallazgos consolidados'!$L$2:$L$5000,"Compartido (BNO + Monific)") -> 58
B24: Monific – TI | C24: =COUNTIF('Hallazgos consolidados'!$L$2:$L$5000,"Monific – TI") -> 17
B25: Monific – negocio (Raquel) | C25: =COUNTIF('Hallazgos consolidados'!$L$2:$L$5000,"Monific – negocio (Raquel)") -> 13
B26: Monific – Compliance | C26: =COUNTIF('Hallazgos consolidados'!$L$2:$L$5000,"Monific – Compliance") -> 6
B27: Despacho externo (ARI) | C27: =COUNTIF('Hallazgos consolidados'!$L$2:$L$5000,"Despacho externo (ARI)") -> 6
B29: Validación Monific (Raquel) — por evidencia
B30: Categoría | C30: Registros
B31: Validado (resuelto) | C31: =COUNTIF('Hallazgos consolidados'!$N$2:$N$5000,"Validado (resuelto)") -> 5
B32: Resuelto (con pendiente menor) | C32: =COUNTIF('Hallazgos consolidados'!$N$2:$N$5000,"Resuelto (con pendiente menor)") -> 1
B33: Resuelto pendiente de confirmar | C33: =COUNTIF('Hallazgos consolidados'!$N$2:$N$5000,"Resuelto pendiente de confirmar") -> 0
B34: Resuelto por TI Monific (Daniel) | C34: =COUNTIF('Hallazgos consolidados'!$N$2:$N$5000,"Resuelto por TI Monific (Daniel)") -> 12
B35: Sigue mal (abierto) | C35: =COUNTIF('Hallazgos consolidados'!$N$2:$N$5000,"Sigue mal (abierto)") -> 125
B36: Sigue mal — BNO reconoció que aplica | C36: =COUNTIF('Hallazgos consolidados'!$N$2:$N$5000,"Sigue mal — BNO reconoció que aplica") -> 103
B37: Sigue mal — verificado por API | C37: =COUNTIF('Hallazgos consolidados'!$N$2:$N$5000,"Sigue mal — verificado por API") -> 6
B38: BNO documentó resuelto pero sigue mal | C38: =COUNTIF('Hallazgos consolidados'!$N$2:$N$5000,"BNO documentó resuelto pero sigue mal") -> 1
B39: Bloqueado — pendiente decisión Monific | C39: =COUNTIF('Hallazgos consolidados'!$N$2:$N$5000,"Bloqueado — pendiente decisión Monific") -> 3
B40: En curso (BNO) | C40: =COUNTIF('Hallazgos consolidados'!$N$2:$N$5000,"En curso (BNO)") -> 3
B41: Pendiente — BNO debe definir | C41: =COUNTIF('Hallazgos consolidados'!$N$2:$N$5000,"Pendiente — BNO debe definir") -> 5
B42: Pendiente — TI Monific | C42: =COUNTIF('Hallazgos consolidados'!$N$2:$N$5000,"Pendiente — TI Monific") -> 3
B43: Descartado por acuerdo de alcance (revisar) | C43: =COUNTIF('Hallazgos consolidados'!$N$2:$N$5000,"Descartado por acuerdo de alcance (revisar)") -> 9
B44: No aplica / informativo | C44: =COUNTIF('Hallazgos consolidados'!$N$2:$N$5000,"No aplica / informativo") -> 6
B45: Sin evidencia objetiva — revisar | C45: =COUNTIF('Hallazgos consolidados'!$N$2:$N$5000,"Sin evidencia objetiva — revisar") -> 0
B47: Resuelto por TI (Daniel)
B48: Categoría | C48: Registros
B49: Sí – Daniel (hecho) | C49: =COUNTIF('Hallazgos consolidados'!$O$2:$O$5000,"Sí – Daniel (hecho)") -> 12
B50: Pendiente TI | C50: =COUNTIF('Hallazgos consolidados'!$O$2:$O$5000,"Pendiente TI") -> 3
B51: Condicionado a BNO | C51: =COUNTIF('Hallazgos consolidados'!$O$2:$O$5000,"Condicionado a BNO") -> 5
B52: No aplica | C52: =COUNTIF('Hallazgos consolidados'!$O$2:$O$5000,"No aplica") -> 264
B54: Comunicaciones TO BE (entregable de BNO)
B55: Categoría | C55: Registros
B56: Total comunicaciones objetivo | C56: =COUNTA('Comunicaciones (81)'!$A$2:$A$5000) -> 81
B57: · A crear | C57: =COUNTIF('Comunicaciones (81)'!$K$2:$K$5000,"Crear") -> 77
B58: · A corregir | C58: =COUNTIF('Comunicaciones (81)'!$K$2:$K$5000,"Corregir") -> 4
B59: · Implementadas (avance) | C59: =COUNTIFS('Comunicaciones (81)'!$A$2:$A$1000,"<>",'Comunicaciones (81)'!$L$2:$L$1000,"<>",'Comunicaciones (81)'!$L$2:$L$1000,"<>No iniciado") -> 0
B60: · No iniciadas (0%) | C60: =COUNTIF('Comunicaciones (81)'!$L$2:$L$5000,"No iniciado") -> 81
B63: Auditoría API — estado real (17-jun-2026)
B64: Indicador | C64: Valor
B65: Workflows activos (ON) | C65: =COUNTIF('WF estado real (96)'!$C$2:$C$5000,"ON") -> 57
B66: Workflows apagados (OFF) | C66: =COUNTIF('WF estado real (96)'!$C$2:$C$5000,"OFF") -> 39
B67: Propiedades de BNO creadas (de 31) | C67: =COUNTIF('Verificación 31 propiedades'!$H$2:$H$5000,"EXISTE*") -> 5
B68: Propiedades de BNO faltantes | C68: =COUNTIF('Verificación 31 propiedades'!$H$2:$H$5000,"NO EXISTE") -> 26

Sheet Acciones TI · Daniel
A1: # | B1: Acción P0/P1 de TI | C1: Estado | D1: Hallazgo(s) vinculado(s) | E1: Nota
A2: 1 | B2: Desactivar Migracion-monific y revocar token legacy (pat-na1-4b023**), tras confirmar que ningún proceso productivo lo usa. | C2: Hecho | D2: APP-001, APP-011
A3: 2 | B3: Reducir scopes de trama1-monific: quitar users.write, crm.export, crm.import, highly_sensitive sin uso. | C3: Hecho | D3: APP-004
A4: 3 | B4: Corregir POST /companies/search: no enviar filtro name cuando el valor esté vacío. | C4: Hecho | D4: APP-006, APP-018
A5: 4 | B5: Implementar upsert de Contactos por email (buscar, PATCH si existe, POST si no). | C5: Pendiente TI | D5: APP-027
A6: 5 | B6: Corregir POST /deals: enviar dropdowns por internalValue, no por label (nombre_de_proyecto). | C6: Hecho | D6: APP-002, APP-038, APP-046, APP-052, APP-056
A7: 6 | B7: Reprocesar/backfill los deals fallidos por encoding (~1,125 entre 1-may y 9-jun). | C7: Pendiente TI | D7: APP-052, APP-038 | E7: Causa raíz corregida (pto.5); falta el backfill.
A8: 7 | B8: Batch nocturno financiero de Contactos: current_account_balance, invested_balance, account_value, current_profit. | C8: Pendiente TI | D8: APP-031, APP-009
A9: 8 | B9: Escribir stp_account_date cuando se cree cuenta STP. | C9: Hecho | D9: APP-025
A10: 9 | B10: Escribir date_first_investment en la primera compra/inversión. | C10: Hecho | D10: APP-026
A11: 10 | B11: Asociar Empresa→Contacto con label «Representante Legal» cuando Admin.Monific marque es_representante_legal=true. | C11: Condicionado a BNO | D11: APP-015 | E11: BNO debe crear primero el association label.
A12: 11 | B12: Crear automáticamente los negocios de Mercado Secundario desde Admin.Monific. | C12: Condicionado a BNO | D12: APP-048, APP-049 | E12: Una vez BNO defina el modelo.
A13: 12 | B13: Implementar Deal padre / asociación deal-deal para reinversiones Molly/Bella. | C13: Condicionado a BNO | D13: APP-042, APP-053 | E13: Si BNO confirma que es factible.
B15: Hecho = 1,2,3,5,8,9 · Pendiente TI = 4,6,7 · Condicionado a BNO = 10,11,12
