Workbook

Sheet Léeme
B1: MONIFIC · Tracker de implementación
B2: Matriz de comunicación TO BE · HubSpot 2026
B4: PROPÓSITO | C4: Seguimiento en tiempo real de la implementación en HubSpot de las 81 comunicaciones definidas en la Matriz completa de comunicación (documento fuente de verdad). BNO actualiza el estado de cada comunicación; Monific valida.
B6: Universo objetivo | C6: 81 comunicaciones: 77 por crear + 4 por corregir. Por área: Solicitantes 22 · Inversionistas 15 · ATC 7 · Cobranza 33 · PDF institucional 4.
B8: Cómo se usa (BNO) | C8: Por cada fila de la pestaña «Tracker», BNO actualiza: Estado de implementación, % avance, Responsable BNO, Fecha objetivo, Fecha real, Link al asset en HubSpot y Notas/Bloqueos. NO se modifican las columnas grises (definición de la matriz).
B9: Cómo se usa (Monific) | C9: Monific revisa lo entregado y marca la columna «Validación Monific» (Pendiente / Validado / Rechazado). El Dashboard se actualiza solo.
B11: Columnas FIJAS (matriz) | C11: ID, Área, Comunicación, Canal, Trigger, Destinatario, Responsable, Propiedad, Tokens, Estado objetivo. Son la definición acordada; no se editan.
B12: Columnas EDITABLES (BNO) | C12: Estado de implementación, % avance, Responsable BNO, Fecha objetivo, Fecha real de implementación, Link al asset HubSpot, Notas / Bloqueos.
B13: Columna EDITABLE (Monific) | C13: Validación Monific.
B15: Estados de implementación | C15: No iniciado · En diseño · En construcción · En pruebas · Implementado · En revisión Monific · Aprobado · Bloqueado. (Lista desplegable)
B16: Estado objetivo | C16: Crear = la comunicación no existe y debe construirse. Corregir = ya existe en HubSpot pero requiere ajuste (4 casos: ATC-001, ATC-007, COB-010, COB-011).
B18: Dashboard | C18: La pestaña «Dashboard» cuenta automáticamente el avance global y por área a partir de la columna «Estado de implementación». No requiere captura manual.
B19: Regla de oro | C19: Esta hoja refleja la matriz; si la matriz cambia, primero se actualiza la matriz y luego esta hoja. La matriz es la fuente de verdad.
B21: Fecha de creación | C21: 16 de junio de 2026 · Portal HubSpot 48427391

Sheet Tracker
A1: TRACKER DE IMPLEMENTACIÓN · MATRIZ DE COMUNICACIÓN TO BE · HUBSPOT MONIFIC 2026
A2: ◄ DEFINICIÓN DE LA MATRIZ (fija — no editar) | K2: SEGUIMIENTO DE IMPLEMENTACIÓN (editable — BNO / Monific) ► | S2: ◆ ACTUALIZACIÓN CTA · 30-jun-2026
A3: ID | B3: Área | C3: Comunicación | D3: Canal | E3: Trigger | F3: Destinatario | G3: Responsable | H3: Propiedad | I3: Tokens | J3: Estado objetivo | K3: Estado de implementación | L3: % avance | M3: Responsable BNO | N3: Fecha objetivo | O3: Fecha real de implementación | P3: Link al asset HubSpot | Q3: Validación Monific | R3: Notas / Bloqueos | S3: CTA · destino / dependencia (Monific)
A4: SOL-001 | B4: Solicitantes | C4: Confirmación de solicitud recibida | D4: Email | E4: Formulario / negocio nuevo | F4: Solicitante | G4: A.A.S. | H4: PB-SOL-NEW | I4: TK-BASE + TK-SOL | J4: Crear | K4: No iniciado | L4: 0 | Q4: Pendiente | S4: RESPONDER · CTA «Responder "Quiero continuar"» → responder al mensaje (correo/WhatsApp). Sin asset ni dependencia de link.
A5: SOL-002 | B5: Solicitantes | C5: Solicitud de documentación inicial | D5: Email | E5: Califica pre-revisión | F5: Solicitante | G5: A.A.S. | H5: PB-SOL-NEW | I5: TK-BASE + TK-SOL | J5: Crear | K5: No iniciado | L5: 0 | Q5: Pendiente | S5: DRIVE · CTA «Cargar documentos» → carpeta del expediente (cta_url = {{deal.link_drive}}). No depende de Monific. Precondición: tarea al A.A.S. (Memo/Guillermo) para crear/compartir la carpeta, disparada por workflow (config BNO; ver SOL-022). El cta_url es el campo {{deal.link_drive}}, que se llena una vez generada la carpeta.
A6: SOL-003 | B6: Solicitantes | C6: Recordatorio documentación día 3 | D6: Email | E6: 3 días sin carga completa | F6: Solicitante | G6: A.A.S. | H6: PB-SOL-NEW | I6: TK-BASE + TK-SOL | J6: Crear | K6: No iniciado | L6: 0 | Q6: Pendiente | S6: DRIVE · CTA «Continuar carga» → carpeta del expediente (cta_url = {{deal.link_drive}}). No depende de Monific. Precondición: tarea al A.A.S. (Memo/Guillermo) para crear/compartir la carpeta, disparada por workflow (config BNO; ver SOL-022). El cta_url es el campo {{deal.link_drive}}, que se llena una vez generada la carpeta.
A7: SOL-004 | B7: Solicitantes | C7: Recordatorio documentación día 6 | D7: Email | E7: 6 días sin carga completa | F7: Solicitante | G7: A.A.S. | H7: PB-SOL-NEW | I7: TK-BASE + TK-SOL | J7: Crear | K7: No iniciado | L7: 0 | Q7: Pendiente | S7: RESPONDER · CTA «Reanudar o pausar» → responder al mensaje (correo/WhatsApp). Sin asset ni dependencia de link.
A8: SOL-005 | B8: Solicitantes | C8: No show o sin respuesta | D8: Email | E8: Cita vencida o 7 días sin respuesta | F8: Solicitante | G8: A.A.S. | H8: PB-SOL-NEW | I8: TK-BASE + TK-SOL | J8: Crear | K8: No iniciado | L8: 0 | Q8: Pendiente | S8: AGENDA · CTA «Reagendar llamada» → página de reuniones (Meetings) en HubSpot. Pendiente BNO: crear la página de agenda de Memo/Guillermo (A.A.S.) y dejar el link de calendario. Monific confirma disponibilidad y conecta el link al cta_url. Dependencia acotada: solo bloquea este asset.
A9: SOL-006 | B9: Solicitantes | C9: Dudas sobre requisitos | D9: Email | E9: Solicitante pide orientación | F9: Solicitante | G9: A.A.S. | H9: PB-SOL-NEW | I9: TK-BASE + TK-SOL | J9: Crear | K9: No iniciado | L9: 0 | Q9: Pendiente | S9: POR DEFINIR · CTA «Ver checklist personalizado» → destino sin asset definido. BNO debe indicar el asset específico (página de estatus/contenido) para fijar el cta_url.
A10: SOL-007 | B10: Solicitantes | C10: Pausa voluntaria | D10: Email | E10: Solicitante decide pausar | F10: Solicitante | G10: A.A.S. | H10: PB-SOL-NEW | I10: TK-BASE + TK-SOL | J10: Crear | K10: No iniciado | L10: 0 | Q10: Pendiente | S10: RESPONDER · CTA «Reactivar solicitud» → responder al mensaje (correo/WhatsApp). Sin asset ni dependencia de link.
A11: SOL-008 | B11: Solicitantes | C11: Carpeta Drive creada | D11: WhatsApp | E11: Carpeta de expediente creada | F11: Solicitante | G11: A.A.S. | H11: PB-SOL-NEW | I11: TK-BASE + TK-SOL | J11: Crear | K11: No iniciado | L11: 0 | Q11: Pendiente | S11: DRIVE · CTA «Abrir carpeta» → carpeta del expediente (cta_url = {{deal.link_drive}}). No depende de Monific. Precondición: tarea al A.A.S. (Memo/Guillermo) para crear/compartir la carpeta, disparada por workflow (config BNO; ver SOL-022). El cta_url es el campo {{deal.link_drive}}, que se llena una vez generada la carpeta.
A12: SOL-009 | B12: Solicitantes | C12: Expediente completo | D12: Email | E12: Validación documental completa | F12: Solicitante | G12: A.A.S. | H12: PB-SOL-NEW | I12: TK-BASE + TK-SOL | J12: Crear | K12: No iniciado | L12: 0 | Q12: Pendiente | S12: POR DEFINIR · CTA «Ver estado de tu solicitud» → destino sin asset definido. BNO debe indicar el asset específico (página de estatus/contenido) para fijar el cta_url.
A13: SOL-010 | B13: Solicitantes | C13: Expediente con observaciones | D13: Email | E13: Validación documental parcial | F13: Solicitante | G13: A.A.S. | H13: PB-SOL-NEW | I13: TK-BASE + TK-SOL | J13: Crear | K13: No iniciado | L13: 0 | Q13: Pendiente | S13: DRIVE · CTA «Corregir observaciones» → carpeta del expediente (cta_url = {{deal.link_drive}}). No depende de Monific. Precondición: tarea al A.A.S. (Memo/Guillermo) para crear/compartir la carpeta, disparada por workflow (config BNO; ver SOL-022). El cta_url es el campo {{deal.link_drive}}, que se llena una vez generada la carpeta.
A14: SOL-011 | B14: Solicitantes | C14: No viable documental | D14: Email | E14: Documentación no subsanable | F14: Solicitante | G14: A.A.S. | H14: PB-SOL-NEW | I14: TK-BASE + TK-SOL | J14: Crear | K14: No iniciado | L14: 0 | Q14: Pendiente | S14: RESPONDER · CTA «Revisar motivo y reactivar» → responder al mensaje (correo/WhatsApp). Sin asset ni dependencia de link.
A15: SOL-012 | B15: Solicitantes | C15: Avance a evaluación financiera | D15: Email | E15: Pasa a análisis financiero | F15: Solicitante | G15: A.A.S. | H15: PB-SOL-NEW | I15: TK-BASE + TK-SOL | J15: Crear | K15: No iniciado | L15: 0 | Q15: Pendiente | S15: POR DEFINIR · CTA «Consultar etapa actual» → destino sin asset definido. BNO debe indicar el asset específico (página de estatus/contenido) para fijar el cta_url.
... A84: PDF-004 | B84: PDF institucional | C84: Carta de refinanciamiento | D84: PDF | E84: Reestructura aprobada | F84: Solicitante | G84: Legal / Owner de pipeline | H84: PB-COB-REFI | I84: TK-BASE + TK-COB + TK-PDF | J84: Crear | K84: No iniciado | L84: 0 | Q84: Pendiente | S84: PDF · CTA «Carta de refinanciamiento» → carta institucional en PDF (ver sección PDFs institucionales). Pendiente BNO: implementar la carta como plantilla prellenable conectada a propiedades; el link se inserta en el cta_url.

Sheet Dashboard
B1: DASHBOARD DE AVANCE
B2: Se actualiza automáticamente desde la pestaña «Tracker»
B4: Avance global por estado de implementación
B5: Estado | C5: Conteo | D5: % del total
B6: No iniciado | C6: =COUNTIF(Tracker!$K$4:$K$84,B6) -> 81 | D6: =IF($C$14=0,0,C6/$C$14) -> 1
B7: En diseño | C7: =COUNTIF(Tracker!$K$4:$K$84,B7) -> 0 | D7: =IF($C$14=0,0,C7/$C$14) -> 0
B8: En construcción | C8: =COUNTIF(Tracker!$K$4:$K$84,B8) -> 0 | D8: =IF($C$14=0,0,C8/$C$14) -> 0
B9: En pruebas | C9: =COUNTIF(Tracker!$K$4:$K$84,B9) -> 0 | D9: =IF($C$14=0,0,C9/$C$14) -> 0
B10: Implementado | C10: =COUNTIF(Tracker!$K$4:$K$84,B10) -> 0 | D10: =IF($C$14=0,0,C10/$C$14) -> 0
B11: En revisión Monific | C11: =COUNTIF(Tracker!$K$4:$K$84,B11) -> 0 | D11: =IF($C$14=0,0,C11/$C$14) -> 0
B12: Aprobado | C12: =COUNTIF(Tracker!$K$4:$K$84,B12) -> 0 | D12: =IF($C$14=0,0,C12/$C$14) -> 0
B13: Bloqueado | C13: =COUNTIF(Tracker!$K$4:$K$84,B13) -> 0 | D13: =IF($C$14=0,0,C13/$C$14) -> 0
B14: TOTAL | C14: =SUM(C6:C13) -> 81 | D14: =IF(C14=0,0,C14/C14) -> 1
B16: Comunicaciones APROBADAS por Monific | C16: =COUNTIF(Tracker!$K$4:$K$84,"Aprobado") -> 0
B17: % de avance global (Aprobado / 81) | C17: =IF($C$14=0,0,C16/$C$14) -> 0
B19: Avance por área
B20: Área | C20: Objetivo | D20: No iniciado | E20: En proceso | F20: Implementado | G20: Aprobado | H20: Bloqueado
B21: Solicitantes | C21: 22 | D21: =COUNTIFS(Tracker!$B$4:$B$84,B21,Tracker!$K$4:$K$84,"No iniciado") -> 22 | E21: =COUNTIFS(Tracker!$B$4:$B$84,B21,Tracker!$K$4:$K$84,"En diseño")+COUNTIFS(Tracker!$B$4:$B$84,B21,Tracker!$K$4:$K$84,"En construcción")+COUNTIFS(Tracker!$B$4:$B$84,B21,Tracker!$K$4:$K$84,"En pruebas")+COUNTIFS(Tracker!$B$4:$B$84,B21,Tracker!$K$4:$K$84,"En revisión Monific") -> 0 | F21: =COUNTIFS(Tracker!$B$4:$B$84,B21,Tracker!$K$4:$K$84,"Implementado") -> 0 | G21: =COUNTIFS(Tracker!$B$4:$B$84,B21,Tracker!$K$4:$K$84,"Aprobado") -> 0 | H21: =COUNTIFS(Tracker!$B$4:$B$84,B21,Tracker!$K$4:$K$84,"Bloqueado") -> 0
B22: Inversionistas | C22: 15 | D22: =COUNTIFS(Tracker!$B$4:$B$84,B22,Tracker!$K$4:$K$84,"No iniciado") -> 15 | E22: =COUNTIFS(Tracker!$B$4:$B$84,B22,Tracker!$K$4:$K$84,"En diseño")+COUNTIFS(Tracker!$B$4:$B$84,B22,Tracker!$K$4:$K$84,"En construcción")+COUNTIFS(Tracker!$B$4:$B$84,B22,Tracker!$K$4:$K$84,"En pruebas")+COUNTIFS(Tracker!$B$4:$B$84,B22,Tracker!$K$4:$K$84,"En revisión Monific") -> 0 | F22: =COUNTIFS(Tracker!$B$4:$B$84,B22,Tracker!$K$4:$K$84,"Implementado") -> 0 | G22: =COUNTIFS(Tracker!$B$4:$B$84,B22,Tracker!$K$4:$K$84,"Aprobado") -> 0 | H22: =COUNTIFS(Tracker!$B$4:$B$84,B22,Tracker!$K$4:$K$84,"Bloqueado") -> 0
B23: ATC | C23: 7 | D23: =COUNTIFS(Tracker!$B$4:$B$84,B23,Tracker!$K$4:$K$84,"No iniciado") -> 7 | E23: =COUNTIFS(Tracker!$B$4:$B$84,B23,Tracker!$K$4:$K$84,"En diseño")+COUNTIFS(Tracker!$B$4:$B$84,B23,Tracker!$K$4:$K$84,"En construcción")+COUNTIFS(Tracker!$B$4:$B$84,B23,Tracker!$K$4:$K$84,"En pruebas")+COUNTIFS(Tracker!$B$4:$B$84,B23,Tracker!$K$4:$K$84,"En revisión Monific") -> 0 | F23: =COUNTIFS(Tracker!$B$4:$B$84,B23,Tracker!$K$4:$K$84,"Implementado") -> 0 | G23: =COUNTIFS(Tracker!$B$4:$B$84,B23,Tracker!$K$4:$K$84,"Aprobado") -> 0 | H23: =COUNTIFS(Tracker!$B$4:$B$84,B23,Tracker!$K$4:$K$84,"Bloqueado") -> 0
B24: Cobranza | C24: 33 | D24: =COUNTIFS(Tracker!$B$4:$B$84,B24,Tracker!$K$4:$K$84,"No iniciado") -> 33 | E24: =COUNTIFS(Tracker!$B$4:$B$84,B24,Tracker!$K$4:$K$84,"En diseño")+COUNTIFS(Tracker!$B$4:$B$84,B24,Tracker!$K$4:$K$84,"En construcción")+COUNTIFS(Tracker!$B$4:$B$84,B24,Tracker!$K$4:$K$84,"En pruebas")+COUNTIFS(Tracker!$B$4:$B$84,B24,Tracker!$K$4:$K$84,"En revisión Monific") -> 0 | F24: =COUNTIFS(Tracker!$B$4:$B$84,B24,Tracker!$K$4:$K$84,"Implementado") -> 0 | G24: =COUNTIFS(Tracker!$B$4:$B$84,B24,Tracker!$K$4:$K$84,"Aprobado") -> 0 | H24: =COUNTIFS(Tracker!$B$4:$B$84,B24,Tracker!$K$4:$K$84,"Bloqueado") -> 0
B25: PDF institucional | C25: 4 | D25: =COUNTIFS(Tracker!$B$4:$B$84,B25,Tracker!$K$4:$K$84,"No iniciado") -> 4 | E25: =COUNTIFS(Tracker!$B$4:$B$84,B25,Tracker!$K$4:$K$84,"En diseño")+COUNTIFS(Tracker!$B$4:$B$84,B25,Tracker!$K$4:$K$84,"En construcción")+COUNTIFS(Tracker!$B$4:$B$84,B25,Tracker!$K$4:$K$84,"En pruebas")+COUNTIFS(Tracker!$B$4:$B$84,B25,Tracker!$K$4:$K$84,"En revisión Monific") -> 0 | F25: =COUNTIFS(Tracker!$B$4:$B$84,B25,Tracker!$K$4:$K$84,"Implementado") -> 0 | G25: =COUNTIFS(Tracker!$B$4:$B$84,B25,Tracker!$K$4:$K$84,"Aprobado") -> 0 | H25: =COUNTIFS(Tracker!$B$4:$B$84,B25,Tracker!$K$4:$K$84,"Bloqueado") -> 0
B26: TOTAL | C26: =SUM(C21:C25) -> 81 | D26: =SUM(D21:D25) -> 81 | E26: =SUM(E21:E25) -> 0 | F26: =SUM(F21:F25) -> 0 | G26: =SUM(G21:G25) -> 0 | H26: =SUM(H21:H25) -> 0
B28: Validación Monific
B29: Validado | C29: =COUNTIF(Tracker!$Q$4:$Q$84,B29) -> 0
B30: Pendiente | C30: =COUNTIF(Tracker!$Q$4:$Q$84,B30) -> 81
B31: Rechazado | C31: =COUNTIF(Tracker!$Q$4:$Q$84,B31) -> 0

Sheet Catálogos
A1: Estado de implementación | B1: Estado objetivo | C1: Validación Monific
A2: No iniciado | B2: Crear | C2: Pendiente
A3: En diseño | B3: Corregir | C3: Validado
A4: En construcción | C4: Rechazado
A5: En pruebas
A6: Implementado
A7: En revisión Monific
A8: Aprobado
A9: Bloqueado
